<SceneObjectGroup><SceneObjectPart xmlns:xsi="http://www.w3.org/2001/XMLSchema-instance" xmlns:xsd="http://www.w3.org/2001/XMLSchema"><AllowedDrop>false</AllowedDrop><CreatorID><Guid>155adad4-8975-4706-b95f-fa75af0678c5</Guid></CreatorID><FolderID><Guid>25c23f68-3f30-4be1-a1ae-6654acf28340</Guid></FolderID><InventorySerial>1</InventorySerial><TaskInventory /><ObjectFlags>0</ObjectFlags><UUID><Guid>25c23f68-3f30-4be1-a1ae-6654acf28340</Guid></UUID><LocalId>1269922121</LocalId><Name>NE Railings</Name><Material>3</Material><PassTouches>false</PassTouches><RegionHandle>1099511628032000</RegionHandle><ScriptAccessPin>0</ScriptAccessPin><PlaySoundSlavePrims /><LoopSoundSlavePrims /><GroupPosition><X>243.517029</X><Y>220</Y><Z>18.8</Z></GroupPosition><OffsetPosition><X>0</X><Y>0</Y><Z>0</Z></OffsetPosition><RotationOffset><X>-0.707106769</X><Y>0</Y><Z>0</Z><W>0.707106769</W></RotationOffset><Velocity><X>0</X><Y>0</Y><Z>0</Z></Velocity><AngularVelocity><X>0</X><Y>0</Y><Z>0</Z></AngularVelocity><Acceleration><X>0</X><Y>0</Y><Z>0</Z></Acceleration><Description>(No Description)</Description><Color /><Text /><SitName /><TouchName /><LinkNum>1</LinkNum><ClickAction>0</ClickAction><Shape><ProfileCurve>1</ProfileCurve><TextureEntry>naXA16koQsqcsGR0nwrBMgAAAAAAAAAAgD8BAACAPgCamZk/AgAAgD8EAACAPwgAAIA/EAAAgD8AAAABzCwAMxMBM/MCAAAEAAAIAAAQAAAAAAAAwAAAAAA=</TextureEntry><ExtraParams>AA==</ExtraParams><PathBegin>0</PathBegin><PathCurve>16</PathCurve><PathEnd>0</PathEnd><PathRadiusOffset>0</PathRadiusOffset><PathRevolutions>0</PathRevolutions><PathScaleX>100</PathScaleX><PathScaleY>100</PathScaleY><PathShearX>0</PathShearX><PathShearY>0</PathShearY><PathSkew>0</PathSkew><PathTaperX>0</PathTaperX><PathTaperY>0</PathTaperY><PathTwist>0</PathTwist><PathTwistBegin>0</PathTwistBegin><PCode>9</PCode><ProfileBegin>0</ProfileBegin><ProfileEnd>0</ProfileEnd><ProfileHollow>0</ProfileHollow><Scale><X>0.5</X><Y>8</Y><Z>0.5</Z></Scale><State>0</State><ProfileShape>Square</ProfileShape><HollowShape>Same</HollowShape><SculptTexture><Guid>00000000-0000-0000-0000-000000000000</Guid></SculptTexture><SculptType>0</SculptType><SculptData /><FlexiSoftness>0</FlexiSoftness><FlexiTension>0</FlexiTension><FlexiDrag>0</FlexiDrag><FlexiGravity>0</FlexiGravity><FlexiWind>0</FlexiWind><FlexiForceX>0</FlexiForceX><FlexiForceY>0</FlexiForceY><FlexiForceZ>0</FlexiForceZ><LightColorR>0</LightColorR><LightColorG>0</LightColorG><LightColorB>0</LightColorB><LightColorA>1</LightColorA><LightRadius>0</LightRadius><LightCutoff>0</LightCutoff><LightFalloff>0</LightFalloff><LightIntensity>1</LightIntensity><FlexiEntry>false</FlexiEntry><LightEntry>false</LightEntry><SculptEntry>false</SculptEntry></Shape><Scale><X>0.5</X><Y>8</Y><Z>0.5</Z></Scale><UpdateFlag>0</UpdateFlag><SitTargetOrientation><X>0</X><Y>0</Y><Z>0</Z><W>1</W></SitTargetOrientation><SitTargetPosition><X>0</X><Y>0</Y><Z>0</Z></SitTargetPosition><SitTargetPositionLL><X>0</X><Y>0</Y><Z>0</Z></SitTargetPositionLL><SitTargetOrientationLL><X>0</X><Y>0</Y><Z>0</Z><W>1</W></SitTargetOrientationLL><ParentID>0</ParentID><CreationDate>1260188722</CreationDate><Category>0</Category><SalePrice>0</SalePrice><ObjectSaleType>0</ObjectSaleType><OwnershipCost>0</OwnershipCost><GroupID><Guid>19b9cf50-f667-4a97-806b-fec7d4363c46</Guid></GroupID><OwnerID><Guid>155adad4-8975-4706-b95f-fa75af0678c5</Guid></OwnerID><LastOwnerID><Guid>155adad4-8975-4706-b95f-fa75af0678c5</Guid></LastOwnerID><BaseMask>2147483647</BaseMask><OwnerMask>2147483647</OwnerMask><GroupMask>0</GroupMask><EveryoneMask>0</EveryoneMask><NextOwnerMask>581632</NextOwnerMask><Flags>None</Flags><CollisionSound><Guid>00000000-0000-0000-0000-000000000000</Guid></CollisionSound><CollisionSoundVolume>0</CollisionSoundVolume></SceneObjectPart><OtherParts><SceneObjectPart xmlns:xsi="http://www.w3.org/2001/XMLSchema-instance" xmlns:xsd="http://www.w3.org/2001/XMLSchema"><AllowedDrop>false</AllowedDrop><CreatorID><Guid>155adad4-8975-4706-b95f-fa75af0678c5</Guid></CreatorID><FolderID><Guid>401493e1-8f7f-4d82-836f-489b63ae2caf</Guid></FolderID><InventorySerial>1</InventorySerial><TaskInventory /><ObjectFlags>0</ObjectFlags><UUID><Guid>401493e1-8f7f-4d82-836f-489b63ae2caf</Guid></UUID><LocalId>1269922122</LocalId><Name>OV wall angled</Name><Material>3</Material><PassTouches>false</PassTouches><RegionHandle>1099511628032000</RegionHandle><ScriptAccessPin>0</ScriptAccessPin><PlaySoundSlavePrims /><LoopSoundSlavePrims /><GroupPosition><X>243.517029</X><Y>220</Y><Z>18.8</Z></GroupPosition><OffsetPosition><X>0</X><Y>0</Y><Z>-8</Z></OffsetPosition><RotationOffset><X>0</X><Y>0</Y><Z>0</Z><W>1</W></RotationOffset><Velocity><X>0</X><Y>0</Y><Z>0</Z></Velocity><AngularVelocity><X>0</X><Y>0</Y><Z>0</Z></AngularVelocity><Acceleration><X>0</X><Y>0</Y><Z>0</Z></Acceleration><Description>(No Description)</Description><Color /><Text /><SitName /><TouchName /><LinkNum>2</LinkNum><ClickAction>0</ClickAction><Shape><ProfileCurve>1</ProfileCurve><TextureEntry>naXA16koQsqcsGR0nwrBMgAAAAAAAAAAgD8BAACAPgCamZk/AgAAgD8EAACAPwgAAIA/EAAAgD8AAAABzCwAMxMBM/MCAAAEAAAIAAAQAAAAAAAAwAAAAAA=</TextureEntry><ExtraParams>AA==</ExtraParams><PathBegin>0</PathBegin><PathCurve>16</PathCurve><PathEnd>0</PathEnd><PathRadiusOffset>0</PathRadiusOffset><PathRevolutions>0</PathRevolutions><PathScaleX>100</PathScaleX><PathScaleY>100</PathScaleY><PathShearX>0</PathShearX><PathShearY>0</PathShearY><PathSkew>0</PathSkew><PathTaperX>0</PathTaperX><PathTaperY>0</PathTaperY><PathTwist>0</PathTwist><PathTwistBegin>0</PathTwistBegin><PCode>9</PCode><ProfileBegin>0</ProfileBegin><ProfileEnd>0</ProfileEnd><ProfileHollow>0</ProfileHollow><Scale><X>0.5</X><Y>8</Y><Z>0.5</Z></Scale><State>0</State><ProfileShape>Square</ProfileShape><HollowShape>Same</HollowShape><SculptTexture><Guid>00000000-0000-0000-0000-000000000000</Guid></SculptTexture><SculptType>0</SculptType><SculptData /><FlexiSoftness>0</FlexiSoftness><FlexiTension>0</FlexiTension><FlexiDrag>0</FlexiDrag><FlexiGravity>0</FlexiGravity><FlexiWind>0</FlexiWind><FlexiForceX>0</FlexiForceX><FlexiForceY>0</FlexiForceY><FlexiForceZ>0</FlexiForceZ><LightColorR>0</LightColorR><LightColorG>0</LightColorG><LightColorB>0</LightColorB><LightColorA>1</LightColorA><LightRadius>0</LightRadius><LightCutoff>0</LightCutoff><LightFalloff>0</LightFalloff><LightIntensity>1</LightIntensity><FlexiEntry>false</FlexiEntry><LightEntry>false</LightEntry><SculptEntry>false</SculptEntry></Shape><Scale><X>0.5</X><Y>8</Y><Z>0.5</Z></Scale><UpdateFlag>0</UpdateFlag><SitTargetOrientation><X>0</X><Y>0</Y><Z>0</Z><W>1</W></SitTargetOrientation><SitTargetPosition><X>0</X><Y>0</Y><Z>0</Z></SitTargetPosition><SitTargetPositionLL><X>0</X><Y>0</Y><Z>0</Z></SitTargetPositionLL><SitTargetOrientationLL><X>0</X><Y>0</Y><Z>0</Z><W>1</W></SitTargetOrientationLL><ParentID>1269922121</ParentID><CreationDate>1260188722</CreationDate><Category>0</Category><SalePrice>10</SalePrice><ObjectSaleType>0</ObjectSaleType><OwnershipCost>0</OwnershipCost><GroupID><Guid>19b9cf50-f667-4a97-806b-fec7d4363c46</Guid></GroupID><OwnerID><Guid>155adad4-8975-4706-b95f-fa75af0678c5</Guid></OwnerID><LastOwnerID><Guid>155adad4-8975-4706-b95f-fa75af0678c5</Guid></LastOwnerID><BaseMask>2147483647</BaseMask><OwnerMask>2147483647</OwnerMask><GroupMask>0</GroupMask><EveryoneMask>0</EveryoneMask><NextOwnerMask>581632</NextOwnerMask><Flags>None</Flags><CollisionSound><Guid>00000000-0000-0000-0000-000000000000</Guid></CollisionSound><CollisionSoundVolume>0</CollisionSoundVolume></SceneObjectPart><SceneObjectPart xmlns:xsi="http://www.w3.org/2001/XMLSchema-instance" xmlns:xsd="http://www.w3.org/2001/XMLSchema"><AllowedDrop>false</AllowedDrop><CreatorID><Guid>155adad4-8975-4706-b95f-fa75af0678c5</Guid></CreatorID><FolderID><Guid>ba43bb3f-2b6d-413b-a86a-edbfaf27bafd</Guid></FolderID><InventorySerial>1</InventorySerial><TaskInventory /><ObjectFlags>0</ObjectFlags><UUID><Guid>ba43bb3f-2b6d-413b-a86a-edbfaf27bafd</Guid></UUID><LocalId>1269922123</LocalId><Name>OpenVCE - straight rail 24m</Name><Material>3</Material><PassTouches>false</PassTouches><RegionHandle>1099511628032000</RegionHandle><ScriptAccessPin>0</ScriptAccessPin><PlaySoundSlavePrims /><LoopSoundSlavePrims /><GroupPosition><X>243.517029</X><Y>220</Y><Z>18.8</Z></GroupPosition><OffsetPosition><X>0</X><Y>-3.8447876</Y><Z>-11.8745861</Z></OffsetPosition><RotationOffset><X>-0.706760943</X><Y>-0.0002442076</Y><Z>0.000244011346</Z><W>0.707452357</W></RotationOffset><Velocity><X>0</X><Y>0</Y><Z>0</Z></Velocity><AngularVelocity><X>0</X><Y>0</Y><Z>0</Z></AngularVelocity><Acceleration><X>0</X><Y>0</Y><Z>0</Z></Acceleration><Description /><Color /><Text /><SitName /><TouchName /><LinkNum>3</LinkNum><ClickAction>0</ClickAction><Shape><ProfileCurve>1</ProfileCurve><TextureEntry>naXA16koQsqcsGR0nwrBMgAAAAAAAAAAgD8AAACAPwSkcH0/EKRwfT8AAAAAAAAAAAAAwAAAAAA=</TextureEntry><ExtraParams>AA==</ExtraParams><PathBegin>0</PathBegin><PathCurve>16</PathCurve><PathEnd>0</PathEnd><PathRadiusOffset>0</PathRadiusOffset><PathRevolutions>0</PathRevolutions><PathScaleX>100</PathScaleX><PathScaleY>100</PathScaleY><PathShearX>0</PathShearX><PathShearY>0</PathShearY><PathSkew>0</PathSkew><PathTaperX>0</PathTaperX><PathTaperY>0</PathTaperY><PathTwist>0</PathTwist><PathTwistBegin>0</PathTwistBegin><PCode>9</PCode><ProfileBegin>0</ProfileBegin><ProfileEnd>0</ProfileEnd><ProfileHollow>0</ProfileHollow><Scale><X>0.15</X><Y>8</Y><Z>0.15</Z></Scale><State>0</State><ProfileShape>Square</ProfileShape><HollowShape>Same</HollowShape><SculptTexture><Guid>00000000-0000-0000-0000-000000000000</Guid></SculptTexture><SculptType>0</SculptType><SculptData /><FlexiSoftness>0</FlexiSoftness><FlexiTension>0</FlexiTension><FlexiDrag>0</FlexiDrag><FlexiGravity>0</FlexiGravity><FlexiWind>0</FlexiWind><FlexiForceX>0</FlexiForceX><FlexiForceY>0</FlexiForceY><FlexiForceZ>0</FlexiForceZ><LightColorR>0</LightColorR><LightColorG>0</LightColorG><LightColorB>0</LightColorB><LightColorA>1</LightColorA><LightRadius>0</LightRadius><LightCutoff>0</LightCutoff><LightFalloff>0</LightFalloff><LightIntensity>1</LightIntensity><FlexiEntry>false</FlexiEntry><LightEntry>false</LightEntry><SculptEntry>false</SculptEntry></Shape><Scale><X>0.15</X><Y>8</Y><Z>0.15</Z></Scale><UpdateFlag>0</UpdateFlag><SitTargetOrientation><X>0</X><Y>0</Y><Z>0</Z><W>1</W></SitTargetOrientation><SitTargetPosition><X>0</X><Y>0</Y><Z>0</Z></SitTargetPosition><SitTargetPositionLL><X>0</X><Y>0</Y><Z>0</Z></SitTargetPositionLL><SitTargetOrientationLL><X>0</X><Y>0</Y><Z>0</Z><W>1</W></SitTargetOrientationLL><ParentID>1269922121</ParentID><CreationDate>1260188722</CreationDate><Category>0</Category><SalePrice>10</SalePrice><ObjectSaleType>0</ObjectSaleType><OwnershipCost>0</OwnershipCost><GroupID><Guid>19b9cf50-f667-4a97-806b-fec7d4363c46</Guid></GroupID><OwnerID><Guid>155adad4-8975-4706-b95f-fa75af0678c5</Guid></OwnerID><LastOwnerID><Guid>155adad4-8975-4706-b95f-fa75af0678c5</Guid></LastOwnerID><BaseMask>2147483647</BaseMask><OwnerMask>2147483647</OwnerMask><GroupMask>0</GroupMask><EveryoneMask>0</EveryoneMask><NextOwnerMask>581632</NextOwnerMask><Flags>None</Flags><CollisionSound><Guid>00000000-0000-0000-0000-000000000000</Guid></CollisionSound><CollisionSoundVolume>0</CollisionSoundVolume></SceneObjectPart><SceneObjectPart xmlns:xsi="http://www.w3.org/2001/XMLSchema-instance" xmlns:xsd="http://www.w3.org/2001/XMLSchema"><AllowedDrop>false</AllowedDrop><CreatorID><Guid>155adad4-8975-4706-b95f-fa75af0678c5</Guid></CreatorID><FolderID><Guid>1cf9f3e6-c325-4b9d-8c36-f5d6f6192894</Guid></FolderID><InventorySerial>1</InventorySerial><TaskInventory /><ObjectFlags>0</ObjectFlags><UUID><Guid>1cf9f3e6-c325-4b9d-8c36-f5d6f6192894</Guid></UUID><LocalId>1269922124</LocalId><Name>rail</Name><Material>3</Material><PassTouches>false</PassTouches><RegionHandle>1099511628032000</RegionHandle><ScriptAccessPin>0</ScriptAccessPin><PlaySoundSlavePrims /><LoopSoundSlavePrims /><GroupPosition><X>243.517029</X><Y>220</Y><Z>18.8</Z></GroupPosition><OffsetPosition><X>0</X><Y>-3.850006</Y><Z>-4</Z></OffsetPosition><RotationOffset><X>-0.7067613</X><Y>0</Y><Z>0</Z><W>0.7074521</W></RotationOffset><Velocity><X>0</X><Y>0</Y><Z>0</Z></Velocity><AngularVelocity><X>0</X><Y>0</Y><Z>0</Z></AngularVelocity><Acceleration><X>0</X><Y>0</Y><Z>0</Z></Acceleration><Description>(No Description)</Description><Color /><Text /><SitName /><TouchName /><LinkNum>4</LinkNum><ClickAction>0</ClickAction><Shape><ProfileCurve>1</ProfileCurve><TextureEntry>naXA16koQsqcsGR0nwrBMgAAAAAAAAAAgD8AAACAPwSkcH0/EKRwfT8AAAAAAAAAAAAAwAAAAAA=</TextureEntry><ExtraParams>AA==</ExtraParams><PathBegin>0</PathBegin><PathCurve>16</PathCurve><PathEnd>0</PathEnd><PathRadiusOffset>0</PathRadiusOffset><PathRevolutions>0</PathRevolutions><PathScaleX>100</PathScaleX><PathScaleY>100</PathScaleY><PathShearX>0</PathShearX><PathShearY>0</PathShearY><PathSkew>0</PathSkew><PathTaperX>0</PathTaperX><PathTaperY>0</PathTaperY><PathTwist>0</PathTwist><PathTwistBegin>0</PathTwistBegin><PCode>9</PCode><ProfileBegin>0</ProfileBegin><ProfileEnd>0</ProfileEnd><ProfileHollow>0</ProfileHollow><Scale><X>0.15</X><Y>7.749526</Y><Z>0.15</Z></Scale><State>0</State><ProfileShape>Square</ProfileShape><HollowShape>Same</HollowShape><SculptTexture><Guid>00000000-0000-0000-0000-000000000000</Guid></SculptTexture><SculptType>0</SculptType><SculptData /><FlexiSoftness>0</FlexiSoftness><FlexiTension>0</FlexiTension><FlexiDrag>0</FlexiDrag><FlexiGravity>0</FlexiGravity><FlexiWind>0</FlexiWind><FlexiForceX>0</FlexiForceX><FlexiForceY>0</FlexiForceY><FlexiForceZ>0</FlexiForceZ><LightColorR>0</LightColorR><LightColorG>0</LightColorG><LightColorB>0</LightColorB><LightColorA>1</LightColorA><LightRadius>0</LightRadius><LightCutoff>0</LightCutoff><LightFalloff>0</LightFalloff><LightIntensity>1</LightIntensity><FlexiEntry>false</FlexiEntry><LightEntry>false</LightEntry><SculptEntry>false</SculptEntry></Shape><Scale><X>0.15</X><Y>7.749526</Y><Z>0.15</Z></Scale><UpdateFlag>0</UpdateFlag><SitTargetOrientation><X>0</X><Y>0</Y><Z>0</Z><W>1</W></SitTargetOrientation><SitTargetPosition><X>0</X><Y>0</Y><Z>0</Z></SitTargetPosition><SitTargetPositionLL><X>0</X><Y>0</Y><Z>0</Z></SitTargetPositionLL><SitTargetOrientationLL><X>0</X><Y>0</Y><Z>0</Z><W>1</W></SitTargetOrientationLL><ParentID>1269922121</ParentID><CreationDate>1260188722</CreationDate><Category>0</Category><SalePrice>10</SalePrice><ObjectSaleType>0</ObjectSaleType><OwnershipCost>0</OwnershipCost><GroupID><Guid>19b9cf50-f667-4a97-806b-fec7d4363c46</Guid></GroupID><OwnerID><Guid>155adad4-8975-4706-b95f-fa75af0678c5</Guid></OwnerID><LastOwnerID><Guid>155adad4-8975-4706-b95f-fa75af0678c5</Guid></LastOwnerID><BaseMask>2147483647</BaseMask><OwnerMask>2147483647</OwnerMask><GroupMask>0</GroupMask><EveryoneMask>0</EveryoneMask><NextOwnerMask>581632</NextOwnerMask><Flags>None</Flags><CollisionSound><Guid>00000000-0000-0000-0000-000000000000</Guid></CollisionSound><CollisionSoundVolume>0</CollisionSoundVolume></SceneObjectPart><SceneObjectPart xmlns:xsi="http://www.w3.org/2001/XMLSchema-instance" xmlns:xsd="http://www.w3.org/2001/XMLSchema"><AllowedDrop>false</AllowedDrop><CreatorID><Guid>155adad4-8975-4706-b95f-fa75af0678c5</Guid></CreatorID><FolderID><Guid>93a629ef-c35d-4c35-8f3d-38733416cf15</Guid></FolderID><InventorySerial>1</InventorySerial><TaskInventory /><ObjectFlags>0</ObjectFlags><UUID><Guid>93a629ef-c35d-4c35-8f3d-38733416cf15</Guid></UUID><LocalId>1269922125</LocalId><Name>rail</Name><Material>3</Material><PassTouches>false</PassTouches><RegionHandle>1099511628032000</RegionHandle><ScriptAccessPin>0</ScriptAccessPin><PlaySoundSlavePrims /><LoopSoundSlavePrims /><GroupPosition><X>243.517029</X><Y>220</Y><Z>18.8</Z></GroupPosition><OffsetPosition><X>0</X><Y>-3.84999084</Y><Z>28</Z></OffsetPosition><RotationOffset><X>-0.7067614</X><Y>0</Y><Z>0</Z><W>0.707452</W></RotationOffset><Velocity><X>0</X><Y>0</Y><Z>0</Z></Velocity><AngularVelocity><X>0</X><Y>0</Y><Z>0</Z></AngularVelocity><Acceleration><X>0</X><Y>0</Y><Z>0</Z></Acceleration><Description>(No Description)</Description><Color /><Text /><SitName /><TouchName /><LinkNum>5</LinkNum><ClickAction>0</ClickAction><Shape><ProfileCurve>1</ProfileCurve><TextureEntry>naXA16koQsqcsGR0nwrBMgAAAAAAAAAAgD8AAACAPwSkcH0/EKRwfT8AAAAAAAAAAAAAwAAAAAA=</TextureEntry><ExtraParams>AA==</ExtraParams><PathBegin>0</PathBegin><PathCurve>16</PathCurve><PathEnd>0</PathEnd><PathRadiusOffset>0</PathRadiusOffset><PathRevolutions>0</PathRevolutions><PathScaleX>100</PathScaleX><PathScaleY>100</PathScaleY><PathShearX>0</PathShearX><PathShearY>0</PathShearY><PathSkew>0</PathSkew><PathTaperX>0</PathTaperX><PathTaperY>0</PathTaperY><PathTwist>0</PathTwist><PathTwistBegin>0</PathTwistBegin><PCode>9</PCode><ProfileBegin>0</ProfileBegin><ProfileEnd>0</ProfileEnd><ProfileHollow>0</ProfileHollow><Scale><X>0.15</X><Y>7.749526</Y><Z>0.15</Z></Scale><State>0</State><ProfileShape>Square</ProfileShape><HollowShape>Same</HollowShape><SculptTexture><Guid>00000000-0000-0000-0000-000000000000</Guid></SculptTexture><SculptType>0</SculptType><SculptData /><FlexiSoftness>0</FlexiSoftness><FlexiTension>0</FlexiTension><FlexiDrag>0</FlexiDrag><FlexiGravity>0</FlexiGravity><FlexiWind>0</FlexiWind><FlexiForceX>0</FlexiForceX><FlexiForceY>0</FlexiForceY><FlexiForceZ>0</FlexiForceZ><LightColorR>0</LightColorR><LightColorG>0</LightColorG><LightColorB>0</LightColorB><LightColorA>1</LightColorA><LightRadius>0</LightRadius><LightCutoff>0</LightCutoff><LightFalloff>0</LightFalloff><LightIntensity>1</LightIntensity><FlexiEntry>false</FlexiEntry><LightEntry>false</LightEntry><SculptEntry>false</SculptEntry></Shape><Scale><X>0.15</X><Y>7.749526</Y><Z>0.15</Z></Scale><UpdateFlag>0</UpdateFlag><SitTargetOrientation><X>0</X><Y>0</Y><Z>0</Z><W>1</W></SitTargetOrientation><SitTargetPosition><X>0</X><Y>0</Y><Z>0</Z></SitTargetPosition><SitTargetPositionLL><X>0</X><Y>0</Y><Z>0</Z></SitTargetPositionLL><SitTargetOrientationLL><X>0</X><Y>0</Y><Z>0</Z><W>1</W></SitTargetOrientationLL><ParentID>1269922121</ParentID><CreationDate>1260188723</CreationDate><Category>0</Category><SalePrice>10</SalePrice><ObjectSaleType>0</ObjectSaleType><OwnershipCost>0</OwnershipCost><GroupID><Guid>19b9cf50-f667-4a97-806b-fec7d4363c46</Guid></GroupID><OwnerID><Guid>155adad4-8975-4706-b95f-fa75af0678c5</Guid></OwnerID><LastOwnerID><Guid>155adad4-8975-4706-b95f-fa75af0678c5</Guid></LastOwnerID><BaseMask>2147483647</BaseMask><OwnerMask>2147483647</OwnerMask><GroupMask>0</GroupMask><EveryoneMask>0</EveryoneMask><NextOwnerMask>581632</NextOwnerMask><Flags>None</Flags><CollisionSound><Guid>00000000-0000-0000-0000-000000000000</Guid></CollisionSound><CollisionSoundVolume>0</CollisionSoundVolume></SceneObjectPart><SceneObjectPart xmlns:xsi="http://www.w3.org/2001/XMLSchema-instance" xmlns:xsd="http://www.w3.org/2001/XMLSchema"><AllowedDrop>false</AllowedDrop><CreatorID><Guid>155adad4-8975-4706-b95f-fa75af0678c5</Guid></CreatorID><FolderID><Guid>06fd24e9-9c1c-4c47-b9af-570d9eca521c</Guid></FolderID><InventorySerial>1</InventorySerial><TaskInventory /><ObjectFlags>0</ObjectFlags><UUID><Guid>06fd24e9-9c1c-4c47-b9af-570d9eca521c</Guid></UUID><LocalId>1269922126</LocalId><Name>OpenVCE - straight rail 24m</Name><Material>3</Material><PassTouches>false</PassTouches><RegionHandle>1099511628032000</RegionHandle><ScriptAccessPin>0</ScriptAccessPin><PlaySoundSlavePrims /><LoopSoundSlavePrims /><GroupPosition><X>243.517029</X><Y>220</Y><Z>18.8</Z></GroupPosition><OffsetPosition><X>0</X><Y>-3.8447876</Y><Z>20.1253967</Z></OffsetPosition><RotationOffset><X>-0.706761062</X><Y>-0.000244207651</Y><Z>0.0002440114</Z><W>0.707452238</W></RotationOffset><Velocity><X>0</X><Y>0</Y><Z>0</Z></Velocity><AngularVelocity><X>0</X><Y>0</Y><Z>0</Z></AngularVelocity><Acceleration><X>0</X><Y>0</Y><Z>0</Z></Acceleration><Description /><Color /><Text /><SitName /><TouchName /><LinkNum>6</LinkNum><ClickAction>0</ClickAction><Shape><ProfileCurve>1</ProfileCurve><TextureEntry>naXA16koQsqcsGR0nwrBMgAAAAAAAAAAgD8AAACAPwSkcH0/EKRwfT8AAAAAAAAAAAAAwAAAAAA=</TextureEntry><ExtraParams>AA==</ExtraParams><PathBegin>0</PathBegin><PathCurve>16</PathCurve><PathEnd>0</PathEnd><PathRadiusOffset>0</PathRadiusOffset><PathRevolutions>0</PathRevolutions><PathScaleX>100</PathScaleX><PathScaleY>100</PathScaleY><PathShearX>0</PathShearX><PathShearY>0</PathShearY><PathSkew>0</PathSkew><PathTaperX>0</PathTaperX><PathTaperY>0</PathTaperY><PathTwist>0</PathTwist><PathTwistBegin>0</PathTwistBegin><PCode>9</PCode><ProfileBegin>0</ProfileBegin><ProfileEnd>0</ProfileEnd><ProfileHollow>0</ProfileHollow><Scale><X>0.15</X><Y>8</Y><Z>0.15</Z></Scale><State>0</State><ProfileShape>Square</ProfileShape><HollowShape>Same</HollowShape><SculptTexture><Guid>00000000-0000-0000-0000-000000000000</Guid></SculptTexture><SculptType>0</SculptType><SculptData /><FlexiSoftness>0</FlexiSoftness><FlexiTension>0</FlexiTension><FlexiDrag>0</FlexiDrag><FlexiGravity>0</FlexiGravity><FlexiWind>0</FlexiWind><FlexiForceX>0</FlexiForceX><FlexiForceY>0</FlexiForceY><FlexiForceZ>0</FlexiForceZ><LightColorR>0</LightColorR><LightColorG>0</LightColorG><LightColorB>0</LightColorB><LightColorA>1</LightColorA><LightRadius>0</LightRadius><LightCutoff>0</LightCutoff><LightFalloff>0</LightFalloff><LightIntensity>1</LightIntensity><FlexiEntry>false</FlexiEntry><LightEntry>false</LightEntry><SculptEntry>false</SculptEntry></Shape><Scale><X>0.15</X><Y>8</Y><Z>0.15</Z></Scale><UpdateFlag>0</UpdateFlag><SitTargetOrientation><X>0</X><Y>0</Y><Z>0</Z><W>1</W></SitTargetOrientation><SitTargetPosition><X>0</X><Y>0</Y><Z>0</Z></SitTargetPosition><SitTargetPositionLL><X>0</X><Y>0</Y><Z>0</Z></SitTargetPositionLL><SitTargetOrientationLL><X>0</X><Y>0</Y><Z>0</Z><W>1</W></SitTargetOrientationLL><ParentID>1269922121</ParentID><CreationDate>1260188723</CreationDate><Category>0</Category><SalePrice>10</SalePrice><ObjectSaleType>0</ObjectSaleType><OwnershipCost>0</OwnershipCost><GroupID><Guid>19b9cf50-f667-4a97-806b-fec7d4363c46</Guid></GroupID><OwnerID><Guid>155adad4-8975-4706-b95f-fa75af0678c5</Guid></OwnerID><LastOwnerID><Guid>155adad4-8975-4706-b95f-fa75af0678c5</Guid></LastOwnerID><BaseMask>2147483647</BaseMask><OwnerMask>2147483647</OwnerMask><GroupMask>0</GroupMask><EveryoneMask>0</EveryoneMask><NextOwnerMask>581632</NextOwnerMask><Flags>None</Flags><CollisionSound><Guid>00000000-0000-0000-0000-000000000000</Guid></CollisionSound><CollisionSoundVolume>0</CollisionSoundVolume></SceneObjectPart><SceneObjectPart xmlns:xsi="http://www.w3.org/2001/XMLSchema-instance" xmlns:xsd="http://www.w3.org/2001/XMLSchema"><AllowedDrop>false</AllowedDrop><CreatorID><Guid>155adad4-8975-4706-b95f-fa75af0678c5</Guid></CreatorID><FolderID><Guid>f09aed28-df8a-46aa-a58c-93d7df788319</Guid></FolderID><InventorySerial>1</InventorySerial><TaskInventory /><ObjectFlags>0</ObjectFlags><UUID><Guid>f09aed28-df8a-46aa-a58c-93d7df788319</Guid></UUID><LocalId>1269922127</LocalId><Name>post</Name><Material>3</Material><PassTouches>false</PassTouches><RegionHandle>1099511628032000</RegionHandle><ScriptAccessPin>0</ScriptAccessPin><PlaySoundSlavePrims /><LoopSoundSlavePrims /><GroupPosition><X>243.517029</X><Y>220</Y><Z>18.8</Z></GroupPosition><OffsetPosition><X>0</X><Y>0.00384521484</Y><Z>24</Z></OffsetPosition><RotationOffset><X>-2.1093E-08</X><Y>0.000172644839</Y><Z>1</Z><W>0</W></RotationOffset><Velocity><X>0</X><Y>0</Y><Z>0</Z></Velocity><AngularVelocity><X>0</X><Y>0</Y><Z>0</Z></AngularVelocity><Acceleration><X>0</X><Y>0</Y><Z>0</Z></Acceleration><Description>(No Description)</Description><Color /><Text /><SitName /><TouchName /><LinkNum>7</LinkNum><ClickAction>0</ClickAction><Shape><ProfileCurve>1</ProfileCurve><TextureEntry>naXA16koQsqcsGR0nwrBMgAAAAAAAAAAgD8BAACAPgCamZk/AgAAgD8EAACAPwgAAIA/EAAAgD8AAAABzCwAMxMBM/MCAAAEAAAIAAAQAAAAAAAAwAAAAAA=</TextureEntry><ExtraParams>AA==</ExtraParams><PathBegin>0</PathBegin><PathCurve>16</PathCurve><PathEnd>0</PathEnd><PathRadiusOffset>0</PathRadiusOffset><PathRevolutions>0</PathRevolutions><PathScaleX>100</PathScaleX><PathScaleY>100</PathScaleY><PathShearX>0</PathShearX><PathShearY>0</PathShearY><PathSkew>0</PathSkew><PathTaperX>0</PathTaperX><PathTaperY>0</PathTaperY><PathTwist>0</PathTwist><PathTwistBegin>0</PathTwistBegin><PCode>9</PCode><ProfileBegin>0</ProfileBegin><ProfileEnd>0</ProfileEnd><ProfileHollow>0</ProfileHollow><Scale><X>0.5</X><Y>8</Y><Z>0.5</Z></Scale><State>0</State><ProfileShape>Square</ProfileShape><HollowShape>Same</HollowShape><SculptTexture><Guid>00000000-0000-0000-0000-000000000000</Guid></SculptTexture><SculptType>0</SculptType><SculptData /><FlexiSoftness>0</FlexiSoftness><FlexiTension>0</FlexiTension><FlexiDrag>0</FlexiDrag><FlexiGravity>0</FlexiGravity><FlexiWind>0</FlexiWind><FlexiForceX>0</FlexiForceX><FlexiForceY>0</FlexiForceY><FlexiForceZ>0</FlexiForceZ><LightColorR>0</LightColorR><LightColorG>0</LightColorG><LightColorB>0</LightColorB><LightColorA>1</LightColorA><LightRadius>0</LightRadius><LightCutoff>0</LightCutoff><LightFalloff>0</LightFalloff><LightIntensity>1</LightIntensity><FlexiEntry>false</FlexiEntry><LightEntry>false</LightEntry><SculptEntry>false</SculptEntry></Shape><Scale><X>0.5</X><Y>8</Y><Z>0.5</Z></Scale><UpdateFlag>0</UpdateFlag><SitTargetOrientation><X>0</X><Y>0</Y><Z>0</Z><W>1</W></SitTargetOrientation><SitTargetPosition><X>0</X><Y>0</Y><Z>0</Z></SitTargetPosition><SitTargetPositionLL><X>0</X><Y>0</Y><Z>0</Z></SitTargetPositionLL><SitTargetOrientationLL><X>0</X><Y>0</Y><Z>0</Z><W>1</W></SitTargetOrientationLL><ParentID>1269922121</ParentID><CreationDate>1260188723</CreationDate><Category>0</Category><SalePrice>10</SalePrice><ObjectSaleType>0</ObjectSaleType><OwnershipCost>0</OwnershipCost><GroupID><Guid>19b9cf50-f667-4a97-806b-fec7d4363c46</Guid></GroupID><OwnerID><Guid>155adad4-8975-4706-b95f-fa75af0678c5</Guid></OwnerID><LastOwnerID><Guid>155adad4-8975-4706-b95f-fa75af0678c5</Guid></LastOwnerID><BaseMask>2147483647</BaseMask><OwnerMask>2147483647</OwnerMask><GroupMask>0</GroupMask><EveryoneMask>0</EveryoneMask><NextOwnerMask>581632</NextOwnerMask><Flags>None</Flags><CollisionSound><Guid>00000000-0000-0000-0000-000000000000</Guid></CollisionSound><CollisionSoundVolume>0</CollisionSoundVolume></SceneObjectPart><SceneObjectPart xmlns:xsi="http://www.w3.org/2001/XMLSchema-instance" xmlns:xsd="http://www.w3.org/2001/XMLSchema"><AllowedDrop>false</AllowedDrop><CreatorID><Guid>155adad4-8975-4706-b95f-fa75af0678c5</Guid></CreatorID><FolderID><Guid>f3bbbe95-d960-4042-a025-4525fc2cdaa2</Guid></FolderID><InventorySerial>1</InventorySerial><TaskInventory /><ObjectFlags>0</ObjectFlags><UUID><Guid>f3bbbe95-d960-4042-a025-4525fc2cdaa2</Guid></UUID><LocalId>1269922128</LocalId><Name>post</Name><Material>3</Material><PassTouches>false</PassTouches><RegionHandle>1099511628032000</RegionHandle><ScriptAccessPin>0</ScriptAccessPin><PlaySoundSlavePrims /><LoopSoundSlavePrims /><GroupPosition><X>243.517029</X><Y>220</Y><Z>18.8</Z></GroupPosition><OffsetPosition><X>0</X><Y>0.00384521484</Y><Z>8</Z></OffsetPosition><RotationOffset><X>-2.1093E-08</X><Y>0.000172644839</Y><Z>1</Z><W>0</W></RotationOffset><Velocity><X>0</X><Y>0</Y><Z>0</Z></Velocity><AngularVelocity><X>0</X><Y>0</Y><Z>0</Z></AngularVelocity><Acceleration><X>0</X><Y>0</Y><Z>0</Z></Acceleration><Description>(No Description)</Description><Color /><Text /><SitName /><TouchName /><LinkNum>8</LinkNum><ClickAction>0</ClickAction><Shape><ProfileCurve>1</ProfileCurve><TextureEntry>naXA16koQsqcsGR0nwrBMgAAAAAAAAAAgD8BAACAPgCamZk/AgAAgD8EAACAPwgAAIA/EAAAgD8AAAABzCwAMxMBM/MCAAAEAAAIAAAQAAAAAAAAwAAAAAA=</TextureEntry><ExtraParams>AA==</ExtraParams><PathBegin>0</PathBegin><PathCurve>16</PathCurve><PathEnd>0</PathEnd><PathRadiusOffset>0</PathRadiusOffset><PathRevolutions>0</PathRevolutions><PathScaleX>100</PathScaleX><PathScaleY>100</PathScaleY><PathShearX>0</PathShearX><PathShearY>0</PathShearY><PathSkew>0</PathSkew><PathTaperX>0</PathTaperX><PathTaperY>0</PathTaperY><PathTwist>0</PathTwist><PathTwistBegin>0</PathTwistBegin><PCode>9</PCode><ProfileBegin>0</ProfileBegin><ProfileEnd>0</ProfileEnd><ProfileHollow>0</ProfileHollow><Scale><X>0.5</X><Y>8</Y><Z>0.5</Z></Scale><State>0</State><ProfileShape>Square</ProfileShape><HollowShape>Same</HollowShape><SculptTexture><Guid>00000000-0000-0000-0000-000000000000</Guid></SculptTexture><SculptType>0</SculptType><SculptData /><FlexiSoftness>0</FlexiSoftness><FlexiTension>0</FlexiTension><FlexiDrag>0</FlexiDrag><FlexiGravity>0</FlexiGravity><FlexiWind>0</FlexiWind><FlexiForceX>0</FlexiForceX><FlexiForceY>0</FlexiForceY><FlexiForceZ>0</FlexiForceZ><LightColorR>0</LightColorR><LightColorG>0</LightColorG><LightColorB>0</LightColorB><LightColorA>1</LightColorA><LightRadius>0</LightRadius><LightCutoff>0</LightCutoff><LightFalloff>0</LightFalloff><LightIntensity>1</LightIntensity><FlexiEntry>false</FlexiEntry><LightEntry>false</LightEntry><SculptEntry>false</SculptEntry></Shape><Scale><X>0.5</X><Y>8</Y><Z>0.5</Z></Scale><UpdateFlag>0</UpdateFlag><SitTargetOrientation><X>0</X><Y>0</Y><Z>0</Z><W>1</W></SitTargetOrientation><SitTargetPosition><X>0</X><Y>0</Y><Z>0</Z></SitTargetPosition><SitTargetPositionLL><X>0</X><Y>0</Y><Z>0</Z></SitTargetPositionLL><SitTargetOrientationLL><X>0</X><Y>0</Y><Z>0</Z><W>1</W></SitTargetOrientationLL><ParentID>1269922121</ParentID><CreationDate>1260188723</CreationDate><Category>0</Category><SalePrice>10</SalePrice><ObjectSaleType>0</ObjectSaleType><OwnershipCost>0</OwnershipCost><GroupID><Guid>19b9cf50-f667-4a97-806b-fec7d4363c46</Guid></GroupID><OwnerID><Guid>155adad4-8975-4706-b95f-fa75af0678c5</Guid></OwnerID><LastOwnerID><Guid>155adad4-8975-4706-b95f-fa75af0678c5</Guid></LastOwnerID><BaseMask>2147483647</BaseMask><OwnerMask>2147483647</OwnerMask><GroupMask>0</GroupMask><EveryoneMask>0</EveryoneMask><NextOwnerMask>581632</NextOwnerMask><Flags>None</Flags><CollisionSound><Guid>00000000-0000-0000-0000-000000000000</Guid></CollisionSound><CollisionSoundVolume>0</CollisionSoundVolume></SceneObjectPart><SceneObjectPart xmlns:xsi="http://www.w3.org/2001/XMLSchema-instance" xmlns:xsd="http://www.w3.org/2001/XMLSchema"><AllowedDrop>false</AllowedDrop><CreatorID><Guid>155adad4-8975-4706-b95f-fa75af0678c5</Guid></CreatorID><FolderID><Guid>dca278c6-e3c7-4c80-bb3a-ebf355ef027a</Guid></FolderID><InventorySerial>1</InventorySerial><TaskInventory /><ObjectFlags>0</ObjectFlags><UUID><Guid>dca278c6-e3c7-4c80-bb3a-ebf355ef027a</Guid></UUID><LocalId>1269922129</LocalId><Name>rail</Name><Material>3</Material><PassTouches>false</PassTouches><RegionHandle>1099511628032000</RegionHandle><ScriptAccessPin>0</ScriptAccessPin><PlaySoundSlavePrims /><LoopSoundSlavePrims /><GroupPosition><X>243.517029</X><Y>220</Y><Z>18.8</Z></GroupPosition><OffsetPosition><X>0</X><Y>-3.84999084</Y><Z>12</Z></OffsetPosition><RotationOffset><X>-0.7067614</X><Y>0</Y><Z>0</Z><W>0.707452</W></RotationOffset><Velocity><X>0</X><Y>0</Y><Z>0</Z></Velocity><AngularVelocity><X>0</X><Y>0</Y><Z>0</Z></AngularVelocity><Acceleration><X>0</X><Y>0</Y><Z>0</Z></Acceleration><Description>(No Description)</Description><Color /><Text /><SitName /><TouchName /><LinkNum>9</LinkNum><ClickAction>0</ClickAction><Shape><ProfileCurve>1</ProfileCurve><TextureEntry>naXA16koQsqcsGR0nwrBMgAAAAAAAAAAgD8AAACAPwSkcH0/EKRwfT8AAAAAAAAAAAAAwAAAAAA=</TextureEntry><ExtraParams>AA==</ExtraParams><PathBegin>0</PathBegin><PathCurve>16</PathCurve><PathEnd>0</PathEnd><PathRadiusOffset>0</PathRadiusOffset><PathRevolutions>0</PathRevolutions><PathScaleX>100</PathScaleX><PathScaleY>100</PathScaleY><PathShearX>0</PathShearX><PathShearY>0</PathShearY><PathSkew>0</PathSkew><PathTaperX>0</PathTaperX><PathTaperY>0</PathTaperY><PathTwist>0</PathTwist><PathTwistBegin>0</PathTwistBegin><PCode>9</PCode><ProfileBegin>0</ProfileBegin><ProfileEnd>0</ProfileEnd><ProfileHollow>0</ProfileHollow><Scale><X>0.15</X><Y>7.749526</Y><Z>0.15</Z></Scale><State>0</State><ProfileShape>Square</ProfileShape><HollowShape>Same</HollowShape><SculptTexture><Guid>00000000-0000-0000-0000-000000000000</Guid></SculptTexture><SculptType>0</SculptType><SculptData /><FlexiSoftness>0</FlexiSoftness><FlexiTension>0</FlexiTension><FlexiDrag>0</FlexiDrag><FlexiGravity>0</FlexiGravity><FlexiWind>0</FlexiWind><FlexiForceX>0</FlexiForceX><FlexiForceY>0</FlexiForceY><FlexiForceZ>0</FlexiForceZ><LightColorR>0</LightColorR><LightColorG>0</LightColorG><LightColorB>0</LightColorB><LightColorA>1</LightColorA><LightRadius>0</LightRadius><LightCutoff>0</LightCutoff><LightFalloff>0</LightFalloff><LightIntensity>1</LightIntensity><FlexiEntry>false</FlexiEntry><LightEntry>false</LightEntry><SculptEntry>false</SculptEntry></Shape><Scale><X>0.15</X><Y>7.749526</Y><Z>0.15</Z></Scale><UpdateFlag>0</UpdateFlag><SitTargetOrientation><X>0</X><Y>0</Y><Z>0</Z><W>1</W></SitTargetOrientation><SitTargetPosition><X>0</X><Y>0</Y><Z>0</Z></SitTargetPosition><SitTargetPositionLL><X>0</X><Y>0</Y><Z>0</Z></SitTargetPositionLL><SitTargetOrientationLL><X>0</X><Y>0</Y><Z>0</Z><W>1</W></SitTargetOrientationLL><ParentID>1269922121</ParentID><CreationDate>1260188723</CreationDate><Category>0</Category><SalePrice>10</SalePrice><ObjectSaleType>0</ObjectSaleType><OwnershipCost>0</OwnershipCost><GroupID><Guid>19b9cf50-f667-4a97-806b-fec7d4363c46</Guid></GroupID><OwnerID><Guid>155adad4-8975-4706-b95f-fa75af0678c5</Guid></OwnerID><LastOwnerID><Guid>155adad4-8975-4706-b95f-fa75af0678c5</Guid></LastOwnerID><BaseMask>2147483647</BaseMask><OwnerMask>2147483647</OwnerMask><GroupMask>0</GroupMask><EveryoneMask>0</EveryoneMask><NextOwnerMask>581632</NextOwnerMask><Flags>None</Flags><CollisionSound><Guid>00000000-0000-0000-0000-000000000000</Guid></CollisionSound><CollisionSoundVolume>0</CollisionSoundVolume></SceneObjectPart><SceneObjectPart xmlns:xsi="http://www.w3.org/2001/XMLSchema-instance" xmlns:xsd="http://www.w3.org/2001/XMLSchema"><AllowedDrop>false</AllowedDrop><CreatorID><Guid>155adad4-8975-4706-b95f-fa75af0678c5</Guid></CreatorID><FolderID><Guid>56f062c0-9299-4afb-88d7-5aebc9138379</Guid></FolderID><InventorySerial>1</InventorySerial><TaskInventory /><ObjectFlags>0</ObjectFlags><UUID><Guid>56f062c0-9299-4afb-88d7-5aebc9138379</Guid></UUID><LocalId>1269922130</LocalId><Name>OpenVCE - straight rail 24m</Name><Material>3</Material><PassTouches>false</PassTouches><RegionHandle>1099511628032000</RegionHandle><ScriptAccessPin>0</ScriptAccessPin><PlaySoundSlavePrims /><LoopSoundSlavePrims /><GroupPosition><X>243.517029</X><Y>220</Y><Z>18.8</Z></GroupPosition><OffsetPosition><X>0</X><Y>-3.8447876</Y><Z>4.125412</Z></OffsetPosition><RotationOffset><X>-0.706761062</X><Y>-0.000244207651</Y><Z>0.0002440114</Z><W>0.707452238</W></RotationOffset><Velocity><X>0</X><Y>0</Y><Z>0</Z></Velocity><AngularVelocity><X>0</X><Y>0</Y><Z>0</Z></AngularVelocity><Acceleration><X>0</X><Y>0</Y><Z>0</Z></Acceleration><Description /><Color /><Text /><SitName /><TouchName /><LinkNum>10</LinkNum><ClickAction>0</ClickAction><Shape><ProfileCurve>1</ProfileCurve><TextureEntry>naXA16koQsqcsGR0nwrBMgAAAAAAAAAAgD8AAACAPwSkcH0/EKRwfT8AAAAAAAAAAAAAwAAAAAA=</TextureEntry><ExtraParams>AA==</ExtraParams><PathBegin>0</PathBegin><PathCurve>16</PathCurve><PathEnd>0</PathEnd><PathRadiusOffset>0</PathRadiusOffset><PathRevolutions>0</PathRevolutions><PathScaleX>100</PathScaleX><PathScaleY>100</PathScaleY><PathShearX>0</PathShearX><PathShearY>0</PathShearY><PathSkew>0</PathSkew><PathTaperX>0</PathTaperX><PathTaperY>0</PathTaperY><PathTwist>0</PathTwist><PathTwistBegin>0</PathTwistBegin><PCode>9</PCode><ProfileBegin>0</ProfileBegin><ProfileEnd>0</ProfileEnd><ProfileHollow>0</ProfileHollow><Scale><X>0.15</X><Y>8</Y><Z>0.15</Z></Scale><State>0</State><ProfileShape>Square</ProfileShape><HollowShape>Same</HollowShape><SculptTexture><Guid>00000000-0000-0000-0000-000000000000</Guid></SculptTexture><SculptType>0</SculptType><SculptData /><FlexiSoftness>0</FlexiSoftness><FlexiTension>0</FlexiTension><FlexiDrag>0</FlexiDrag><FlexiGravity>0</FlexiGravity><FlexiWind>0</FlexiWind><FlexiForceX>0</FlexiForceX><FlexiForceY>0</FlexiForceY><FlexiForceZ>0</FlexiForceZ><LightColorR>0</LightColorR><LightColorG>0</LightColorG><LightColorB>0</LightColorB><LightColorA>1</LightColorA><LightRadius>0</LightRadius><LightCutoff>0</LightCutoff><LightFalloff>0</LightFalloff><LightIntensity>1</LightIntensity><FlexiEntry>false</FlexiEntry><LightEntry>false</LightEntry><SculptEntry>false</SculptEntry></Shape><Scale><X>0.15</X><Y>8</Y><Z>0.15</Z></Scale><UpdateFlag>0</UpdateFlag><SitTargetOrientation><X>0</X><Y>0</Y><Z>0</Z><W>1</W></SitTargetOrientation><SitTargetPosition><X>0</X><Y>0</Y><Z>0</Z></SitTargetPosition><SitTargetPositionLL><X>0</X><Y>0</Y><Z>0</Z></SitTargetPositionLL><SitTargetOrientationLL><X>0</X><Y>0</Y><Z>0</Z><W>1</W></SitTargetOrientationLL><ParentID>1269922121</ParentID><CreationDate>1260188723</CreationDate><Category>0</Category><SalePrice>10</SalePrice><ObjectSaleType>0</ObjectSaleType><OwnershipCost>0</OwnershipCost><GroupID><Guid>19b9cf50-f667-4a97-806b-fec7d4363c46</Guid></GroupID><OwnerID><Guid>155adad4-8975-4706-b95f-fa75af0678c5</Guid></OwnerID><LastOwnerID><Guid>155adad4-8975-4706-b95f-fa75af0678c5</Guid></LastOwnerID><BaseMask>2147483647</BaseMask><OwnerMask>2147483647</OwnerMask><GroupMask>0</GroupMask><EveryoneMask>0</EveryoneMask><NextOwnerMask>581632</NextOwnerMask><Flags>None</Flags><CollisionSound><Guid>00000000-0000-0000-0000-000000000000</Guid></CollisionSound><CollisionSoundVolume>0</CollisionSoundVolume></SceneObjectPart><SceneObjectPart xmlns:xsi="http://www.w3.org/2001/XMLSchema-instance" xmlns:xsd="http://www.w3.org/2001/XMLSchema"><AllowedDrop>false</AllowedDrop><CreatorID><Guid>155adad4-8975-4706-b95f-fa75af0678c5</Guid></CreatorID><FolderID><Guid>805c4e9d-9951-4efc-b507-8001248e527e</Guid></FolderID><InventorySerial>1</InventorySerial><TaskInventory /><ObjectFlags>0</ObjectFlags><UUID><Guid>805c4e9d-9951-4efc-b507-8001248e527e</Guid></UUID><LocalId>1269922131</LocalId><Name>post</Name><Material>3</Material><PassTouches>false</PassTouches><RegionHandle>1099511628032000</RegionHandle><ScriptAccessPin>0</ScriptAccessPin><PlaySoundSlavePrims /><LoopSoundSlavePrims /><GroupPosition><X>243.517029</X><Y>220</Y><Z>18.8</Z></GroupPosition><OffsetPosition><X>0</X><Y>0.00384648982</Y><Z>31.7099285</Z></OffsetPosition><RotationOffset><X>-2.1093E-08</X><Y>0.000172644839</Y><Z>1</Z><W>0</W></RotationOffset><Velocity><X>0</X><Y>0</Y><Z>0</Z></Velocity><AngularVelocity><X>0</X><Y>0</Y><Z>0</Z></AngularVelocity><Acceleration><X>0</X><Y>0</Y><Z>0</Z></Acceleration><Description>(No Description)</Description><Color /><Text /><SitName /><TouchName /><LinkNum>11</LinkNum><ClickAction>0</ClickAction><Shape><ProfileCurve>1</ProfileCurve><TextureEntry>naXA16koQsqcsGR0nwrBMgAAAAAAAAAAgD8BAACAPgCamZk/AgAAgD8EAACAPwgAAIA/EAAAgD8AAAABzCwAMxMBM/MCAAAEAAAIAAAQAAAAAAAAwAAAAAA=</TextureEntry><ExtraParams>AA==</ExtraParams><PathBegin>0</PathBegin><PathCurve>16</PathCurve><PathEnd>0</PathEnd><PathRadiusOffset>0</PathRadiusOffset><PathRevolutions>0</PathRevolutions><PathScaleX>100</PathScaleX><PathScaleY>100</PathScaleY><PathShearX>0</PathShearX><PathShearY>0</PathShearY><PathSkew>0</PathSkew><PathTaperX>0</PathTaperX><PathTaperY>0</PathTaperY><PathTwist>0</PathTwist><PathTwistBegin>0</PathTwistBegin><PCode>9</PCode><ProfileBegin>0</ProfileBegin><ProfileEnd>0</ProfileEnd><ProfileHollow>0</ProfileHollow><Scale><X>0.5</X><Y>8</Y><Z>0.5</Z></Scale><State>0</State><ProfileShape>Square</ProfileShape><HollowShape>Same</HollowShape><SculptTexture><Guid>00000000-0000-0000-0000-000000000000</Guid></SculptTexture><SculptType>0</SculptType><SculptData /><FlexiSoftness>0</FlexiSoftness><FlexiTension>0</FlexiTension><FlexiDrag>0</FlexiDrag><FlexiGravity>0</FlexiGravity><FlexiWind>0</FlexiWind><FlexiForceX>0</FlexiForceX><FlexiForceY>0</FlexiForceY><FlexiForceZ>0</FlexiForceZ><LightColorR>0</LightColorR><LightColorG>0</LightColorG><LightColorB>0</LightColorB><LightColorA>1</LightColorA><LightRadius>0</LightRadius><LightCutoff>0</LightCutoff><LightFalloff>0</LightFalloff><LightIntensity>1</LightIntensity><FlexiEntry>false</FlexiEntry><LightEntry>false</LightEntry><SculptEntry>false</SculptEntry></Shape><Scale><X>0.5</X><Y>8</Y><Z>0.5</Z></Scale><UpdateFlag>0</UpdateFlag><SitTargetOrientation><X>0</X><Y>0</Y><Z>0</Z><W>1</W></SitTargetOrientation><SitTargetPosition><X>0</X><Y>0</Y><Z>0</Z></SitTargetPosition><SitTargetPositionLL><X>0</X><Y>0</Y><Z>0</Z></SitTargetPositionLL><SitTargetOrientationLL><X>0</X><Y>0</Y><Z>0</Z><W>1</W></SitTargetOrientationLL><ParentID>1269922121</ParentID><CreationDate>1260188723</CreationDate><Category>0</Category><SalePrice>10</SalePrice><ObjectSaleType>0</ObjectSaleType><OwnershipCost>0</OwnershipCost><GroupID><Guid>19b9cf50-f667-4a97-806b-fec7d4363c46</Guid></GroupID><OwnerID><Guid>155adad4-8975-4706-b95f-fa75af0678c5</Guid></OwnerID><LastOwnerID><Guid>155adad4-8975-4706-b95f-fa75af0678c5</Guid></LastOwnerID><BaseMask>2147483647</BaseMask><OwnerMask>2147483647</OwnerMask><GroupMask>0</GroupMask><EveryoneMask>0</EveryoneMask><NextOwnerMask>581632</NextOwnerMask><Flags>None</Flags><CollisionSound><Guid>00000000-0000-0000-0000-000000000000</Guid></CollisionSound><CollisionSoundVolume>0</CollisionSoundVolume></SceneObjectPart><SceneObjectPart xmlns:xsi="http://www.w3.org/2001/XMLSchema-instance" xmlns:xsd="http://www.w3.org/2001/XMLSchema"><AllowedDrop>false</AllowedDrop><CreatorID><Guid>155adad4-8975-4706-b95f-fa75af0678c5</Guid></CreatorID><FolderID><Guid>dd8560fe-4e4b-47ea-9493-c2c60f78b03b</Guid></FolderID><InventorySerial>1</InventorySerial><TaskInventory /><ObjectFlags>0</ObjectFlags><UUID><Guid>dd8560fe-4e4b-47ea-9493-c2c60f78b03b</Guid></UUID><LocalId>1269922132</LocalId><Name>post</Name><Material>3</Material><PassTouches>false</PassTouches><RegionHandle>1099511628032000</RegionHandle><ScriptAccessPin>0</ScriptAccessPin><PlaySoundSlavePrims /><LoopSoundSlavePrims /><GroupPosition><X>243.517029</X><Y>220</Y><Z>18.8</Z></GroupPosition><OffsetPosition><X>0</X><Y>0.00384521484</Y><Z>16</Z></OffsetPosition><RotationOffset><X>-2.1093E-08</X><Y>0.000172644839</Y><Z>1</Z><W>0</W></RotationOffset><Velocity><X>0</X><Y>0</Y><Z>0</Z></Velocity><AngularVelocity><X>0</X><Y>0</Y><Z>0</Z></AngularVelocity><Acceleration><X>0</X><Y>0</Y><Z>0</Z></Acceleration><Description>(No Description)</Description><Color /><Text /><SitName /><TouchName /><LinkNum>12</LinkNum><ClickAction>0</ClickAction><Shape><ProfileCurve>1</ProfileCurve><TextureEntry>naXA16koQsqcsGR0nwrBMgAAAAAAAAAAgD8BAACAPgCamZk/AgAAgD8EAACAPwgAAIA/EAAAgD8AAAABzCwAMxMBM/MCAAAEAAAIAAAQAAAAAAAAwAAAAAA=</TextureEntry><ExtraParams>AA==</ExtraParams><PathBegin>0</PathBegin><PathCurve>16</PathCurve><PathEnd>0</PathEnd><PathRadiusOffset>0</PathRadiusOffset><PathRevolutions>0</PathRevolutions><PathScaleX>100</PathScaleX><PathScaleY>100</PathScaleY><PathShearX>0</PathShearX><PathShearY>0</PathShearY><PathSkew>0</PathSkew><PathTaperX>0</PathTaperX><PathTaperY>0</PathTaperY><PathTwist>0</PathTwist><PathTwistBegin>0</PathTwistBegin><PCode>9</PCode><ProfileBegin>0</ProfileBegin><ProfileEnd>0</ProfileEnd><ProfileHollow>0</ProfileHollow><Scale><X>0.5</X><Y>8</Y><Z>0.5</Z></Scale><State>0</State><ProfileShape>Square</ProfileShape><HollowShape>Same</HollowShape><SculptTexture><Guid>00000000-0000-0000-0000-000000000000</Guid></SculptTexture><SculptType>0</SculptType><SculptData /><FlexiSoftness>0</FlexiSoftness><FlexiTension>0</FlexiTension><FlexiDrag>0</FlexiDrag><FlexiGravity>0</FlexiGravity><FlexiWind>0</FlexiWind><FlexiForceX>0</FlexiForceX><FlexiForceY>0</FlexiForceY><FlexiForceZ>0</FlexiForceZ><LightColorR>0</LightColorR><LightColorG>0</LightColorG><LightColorB>0</LightColorB><LightColorA>1</LightColorA><LightRadius>0</LightRadius><LightCutoff>0</LightCutoff><LightFalloff>0</LightFalloff><LightIntensity>1</LightIntensity><FlexiEntry>false</FlexiEntry><LightEntry>false</LightEntry><SculptEntry>false</SculptEntry></Shape><Scale><X>0.5</X><Y>8</Y><Z>0.5</Z></Scale><UpdateFlag>0</UpdateFlag><SitTargetOrientation><X>0</X><Y>0</Y><Z>0</Z><W>1</W></SitTargetOrientation><SitTargetPosition><X>0</X><Y>0</Y><Z>0</Z></SitTargetPosition><SitTargetPositionLL><X>0</X><Y>0</Y><Z>0</Z></SitTargetPositionLL><SitTargetOrientationLL><X>0</X><Y>0</Y><Z>0</Z><W>1</W></SitTargetOrientationLL><ParentID>1269922121</ParentID><CreationDate>1260188723</CreationDate><Category>0</Category><SalePrice>10</SalePrice><ObjectSaleType>0</ObjectSaleType><OwnershipCost>0</OwnershipCost><GroupID><Guid>19b9cf50-f667-4a97-806b-fec7d4363c46</Guid></GroupID><OwnerID><Guid>155adad4-8975-4706-b95f-fa75af0678c5</Guid></OwnerID><LastOwnerID><Guid>155adad4-8975-4706-b95f-fa75af0678c5</Guid></LastOwnerID><BaseMask>2147483647</BaseMask><OwnerMask>2147483647</OwnerMask><GroupMask>0</GroupMask><EveryoneMask>0</EveryoneMask><NextOwnerMask>581632</NextOwnerMask><Flags>None</Flags><CollisionSound><Guid>00000000-0000-0000-0000-000000000000</Guid></CollisionSound><CollisionSoundVolume>0</CollisionSoundVolume></SceneObjectPart></OtherParts></SceneObjectGroup>