<SceneObjectGroup><SceneObjectPart xmlns:xsi="http://www.w3.org/2001/XMLSchema-instance" xmlns:xsd="http://www.w3.org/2001/XMLSchema"><AllowedDrop>false</AllowedDrop><CreatorID><Guid>155adad4-8975-4706-b95f-fa75af0678c5</Guid></CreatorID><FolderID><Guid>2e58719a-0f9d-441b-b7fb-2db62d27d77e</Guid></FolderID><InventorySerial>1</InventorySerial><TaskInventory /><ObjectFlags>0</ObjectFlags><UUID><Guid>2e58719a-0f9d-441b-b7fb-2db62d27d77e</Guid></UUID><LocalId>1269920860</LocalId><Name>OpenVCE - Long Planter RHS</Name><Material>3</Material><PassTouches>false</PassTouches><RegionHandle>1099511628032000</RegionHandle><ScriptAccessPin>0</ScriptAccessPin><PlaySoundSlavePrims /><LoopSoundSlavePrims /><GroupPosition><X>76</X><Y>88</Y><Z>21.75</Z></GroupPosition><OffsetPosition><X>0</X><Y>0</Y><Z>0</Z></OffsetPosition><RotationOffset><X>0</X><Y>0</Y><Z>-0.382675439</Z><W>0.923882842</W></RotationOffset><Velocity><X>0</X><Y>0</Y><Z>0</Z></Velocity><AngularVelocity><X>0</X><Y>0</Y><Z>0</Z></AngularVelocity><Acceleration><X>0</X><Y>0</Y><Z>0</Z></Acceleration><Description>Opensim export version</Description><Color /><Text /><SitName /><TouchName /><LinkNum>1</LinkNum><ClickAction>0</ClickAction><Shape><ProfileCurve>1</ProfileCurve><TextureEntry>xzptR3TPRgyWH/Ttp1ZR9gFW7bXCh+ZFrbMlxc0ZJYuVAAAAAAAAAAAAQAAAAABAAAAAAAAAAAAAAMABAAAAAAA=</TextureEntry><ExtraParams>AA==</ExtraParams><PathBegin>0</PathBegin><PathCurve>16</PathCurve><PathEnd>0</PathEnd><PathRadiusOffset>0</PathRadiusOffset><PathRevolutions>0</PathRevolutions><PathScaleX>100</PathScaleX><PathScaleY>100</PathScaleY><PathShearX>0</PathShearX><PathShearY>0</PathShearY><PathSkew>0</PathSkew><PathTaperX>0</PathTaperX><PathTaperY>0</PathTaperY><PathTwist>0</PathTwist><PathTwistBegin>0</PathTwistBegin><PCode>9</PCode><ProfileBegin>0</ProfileBegin><ProfileEnd>0</ProfileEnd><ProfileHollow>0</ProfileHollow><Scale><X>5</X><Y>8</Y><Z>0.2</Z></Scale><State>0</State><ProfileShape>Square</ProfileShape><HollowShape>Same</HollowShape><SculptTexture><Guid>00000000-0000-0000-0000-000000000000</Guid></SculptTexture><SculptType>0</SculptType><SculptData /><FlexiSoftness>0</FlexiSoftness><FlexiTension>0</FlexiTension><FlexiDrag>0</FlexiDrag><FlexiGravity>0</FlexiGravity><FlexiWind>0</FlexiWind><FlexiForceX>0</FlexiForceX><FlexiForceY>0</FlexiForceY><FlexiForceZ>0</FlexiForceZ><LightColorR>0</LightColorR><LightColorG>0</LightColorG><LightColorB>0</LightColorB><LightColorA>1</LightColorA><LightRadius>0</LightRadius><LightCutoff>0</LightCutoff><LightFalloff>0</LightFalloff><LightIntensity>1</LightIntensity><FlexiEntry>false</FlexiEntry><LightEntry>false</LightEntry><SculptEntry>false</SculptEntry></Shape><Scale><X>5</X><Y>8</Y><Z>0.2</Z></Scale><UpdateFlag>0</UpdateFlag><SitTargetOrientation><X>0</X><Y>0</Y><Z>0</Z><W>1</W></SitTargetOrientation><SitTargetPosition><X>0</X><Y>0</Y><Z>0</Z></SitTargetPosition><SitTargetPositionLL><X>0</X><Y>0</Y><Z>0</Z></SitTargetPositionLL><SitTargetOrientationLL><X>0</X><Y>0</Y><Z>0</Z><W>1</W></SitTargetOrientationLL><ParentID>0</ParentID><CreationDate>1258746394</CreationDate><Category>0</Category><SalePrice>10</SalePrice><ObjectSaleType>0</ObjectSaleType><OwnershipCost>0</OwnershipCost><GroupID><Guid>19b9cf50-f667-4a97-806b-fec7d4363c46</Guid></GroupID><OwnerID><Guid>155adad4-8975-4706-b95f-fa75af0678c5</Guid></OwnerID><LastOwnerID><Guid>155adad4-8975-4706-b95f-fa75af0678c5</Guid></LastOwnerID><BaseMask>581632</BaseMask><OwnerMask>581632</OwnerMask><GroupMask>0</GroupMask><EveryoneMask>0</EveryoneMask><NextOwnerMask>581632</NextOwnerMask><Flags>None</Flags><CollisionSound><Guid>00000000-0000-0000-0000-000000000000</Guid></CollisionSound><CollisionSoundVolume>0</CollisionSoundVolume></SceneObjectPart><OtherParts><SceneObjectPart xmlns:xsi="http://www.w3.org/2001/XMLSchema-instance" xmlns:xsd="http://www.w3.org/2001/XMLSchema"><AllowedDrop>false</AllowedDrop><CreatorID><Guid>155adad4-8975-4706-b95f-fa75af0678c5</Guid></CreatorID><FolderID><Guid>af93676e-10fb-4180-bc7c-662dcd401e3a</Guid></FolderID><InventorySerial>1</InventorySerial><TaskInventory /><ObjectFlags>0</ObjectFlags><UUID><Guid>af93676e-10fb-4180-bc7c-662dcd401e3a</Guid></UUID><LocalId>1269920861</LocalId><Name>long planter v2 rhs</Name><Material>3</Material><PassTouches>false</PassTouches><RegionHandle>1099511628032000</RegionHandle><ScriptAccessPin>0</ScriptAccessPin><PlaySoundSlavePrims /><LoopSoundSlavePrims /><GroupPosition><X>76</X><Y>88</Y><Z>21.75</Z></GroupPosition><OffsetPosition><X>-2.88322639</X><Y>-1.106249E-05</Y><Z>-0.683133364</Z></OffsetPosition><RotationOffset><X>1.07222113E-05</X><Y>-0.7071177</Y><Z>1.07056612E-05</Z><W>0.707095861</W></RotationOffset><Velocity><X>0</X><Y>0</Y><Z>0</Z></Velocity><AngularVelocity><X>0</X><Y>0</Y><Z>0</Z></AngularVelocity><Acceleration><X>0</X><Y>0</Y><Z>0</Z></Acceleration><Description>(No Description)</Description><Color /><Text /><SitName /><TouchName /><LinkNum>2</LinkNum><ClickAction>0</ClickAction><Shape><ProfileCurve>1</ProfileCurve><TextureEntry>xzptR3TPRgyWH/Ttp1ZR9gAAAAAAAAAAgD8AAACAPwAAAAAAAAAAAADAAAAAAA==</TextureEntry><ExtraParams>AA==</ExtraParams><PathBegin>0</PathBegin><PathCurve>16</PathCurve><PathEnd>0</PathEnd><PathRadiusOffset>0</PathRadiusOffset><PathRevolutions>0</PathRevolutions><PathScaleX>100</PathScaleX><PathScaleY>100</PathScaleY><PathShearX>0</PathShearX><PathShearY>0</PathShearY><PathSkew>0</PathSkew><PathTaperX>0</PathTaperX><PathTaperY>0</PathTaperY><PathTwist>0</PathTwist><PathTwistBegin>0</PathTwistBegin><PCode>9</PCode><ProfileBegin>0</ProfileBegin><ProfileEnd>0</ProfileEnd><ProfileHollow>0</ProfileHollow><Scale><X>2</X><Y>8</Y><Z>1</Z></Scale><State>0</State><ProfileShape>Square</ProfileShape><HollowShape>Same</HollowShape><SculptTexture><Guid>00000000-0000-0000-0000-000000000000</Guid></SculptTexture><SculptType>0</SculptType><SculptData /><FlexiSoftness>0</FlexiSoftness><FlexiTension>0</FlexiTension><FlexiDrag>0</FlexiDrag><FlexiGravity>0</FlexiGravity><FlexiWind>0</FlexiWind><FlexiForceX>0</FlexiForceX><FlexiForceY>0</FlexiForceY><FlexiForceZ>0</FlexiForceZ><LightColorR>0</LightColorR><LightColorG>0</LightColorG><LightColorB>0</LightColorB><LightColorA>1</LightColorA><LightRadius>0</LightRadius><LightCutoff>0</LightCutoff><LightFalloff>0</LightFalloff><LightIntensity>1</LightIntensity><FlexiEntry>false</FlexiEntry><LightEntry>false</LightEntry><SculptEntry>false</SculptEntry></Shape><Scale><X>2</X><Y>8</Y><Z>1</Z></Scale><UpdateFlag>0</UpdateFlag><SitTargetOrientation><X>0</X><Y>0</Y><Z>0</Z><W>1</W></SitTargetOrientation><SitTargetPosition><X>0</X><Y>0</Y><Z>0</Z></SitTargetPosition><SitTargetPositionLL><X>0</X><Y>0</Y><Z>0</Z></SitTargetPositionLL><SitTargetOrientationLL><X>0</X><Y>0</Y><Z>0</Z><W>1</W></SitTargetOrientationLL><ParentID>1269920860</ParentID><CreationDate>1258746394</CreationDate><Category>0</Category><SalePrice>10</SalePrice><ObjectSaleType>0</ObjectSaleType><OwnershipCost>0</OwnershipCost><GroupID><Guid>19b9cf50-f667-4a97-806b-fec7d4363c46</Guid></GroupID><OwnerID><Guid>155adad4-8975-4706-b95f-fa75af0678c5</Guid></OwnerID><LastOwnerID><Guid>155adad4-8975-4706-b95f-fa75af0678c5</Guid></LastOwnerID><BaseMask>581632</BaseMask><OwnerMask>581632</OwnerMask><GroupMask>0</GroupMask><EveryoneMask>0</EveryoneMask><NextOwnerMask>581632</NextOwnerMask><Flags>None</Flags><CollisionSound><Guid>00000000-0000-0000-0000-000000000000</Guid></CollisionSound><CollisionSoundVolume>0</CollisionSoundVolume></SceneObjectPart><SceneObjectPart xmlns:xsi="http://www.w3.org/2001/XMLSchema-instance" xmlns:xsd="http://www.w3.org/2001/XMLSchema"><AllowedDrop>false</AllowedDrop><CreatorID><Guid>155adad4-8975-4706-b95f-fa75af0678c5</Guid></CreatorID><FolderID><Guid>61dde283-d2d0-4224-9912-44e3c5494f0b</Guid></FolderID><InventorySerial>1</InventorySerial><TaskInventory /><ObjectFlags>0</ObjectFlags><UUID><Guid>61dde283-d2d0-4224-9912-44e3c5494f0b</Guid></UUID><LocalId>1269920862</LocalId><Name>planter</Name><Material>3</Material><PassTouches>false</PassTouches><RegionHandle>1099511628032000</RegionHandle><ScriptAccessPin>0</ScriptAccessPin><PlaySoundSlavePrims /><LoopSoundSlavePrims /><GroupPosition><X>76</X><Y>88</Y><Z>21.75</Z></GroupPosition><OffsetPosition><X>3.254509E-06</X><Y>14.4949951</Y><Z>3.46136517E-07</Z></OffsetPosition><RotationOffset><X>1.14958971E-11</X><Y>-7.58645E-07</Y><Z>9.06993935E-13</Z><W>0.99999994</W></RotationOffset><Velocity><X>0</X><Y>0</Y><Z>0</Z></Velocity><AngularVelocity><X>0</X><Y>0</Y><Z>0</Z></AngularVelocity><Acceleration><X>0</X><Y>0</Y><Z>0</Z></Acceleration><Description /><Color /><Text /><SitName /><TouchName /><LinkNum>3</LinkNum><ClickAction>0</ClickAction><Shape><ProfileCurve>1</ProfileCurve><TextureEntry>xzptR3TPRgyWH/Ttp1ZR9gFW7bXCh+ZFrbMlxc0ZJYuVAAAAAAAAAAAAQAAAAIA/ADJzAAAAAAAAAMABAAAAAAA=</TextureEntry><ExtraParams>AA==</ExtraParams><PathBegin>0</PathBegin><PathCurve>16</PathCurve><PathEnd>0</PathEnd><PathRadiusOffset>0</PathRadiusOffset><PathRevolutions>0</PathRevolutions><PathScaleX>100</PathScaleX><PathScaleY>100</PathScaleY><PathShearX>0</PathShearX><PathShearY>0</PathShearY><PathSkew>0</PathSkew><PathTaperX>0</PathTaperX><PathTaperY>0</PathTaperY><PathTwist>0</PathTwist><PathTwistBegin>0</PathTwistBegin><PCode>9</PCode><ProfileBegin>0</ProfileBegin><ProfileEnd>25000</ProfileEnd><ProfileHollow>0</ProfileHollow><Scale><X>5</X><Y>5</Y><Z>0.2</Z></Scale><State>0</State><ProfileShape>Square</ProfileShape><HollowShape>Same</HollowShape><SculptTexture><Guid>00000000-0000-0000-0000-000000000000</Guid></SculptTexture><SculptType>0</SculptType><SculptData /><FlexiSoftness>0</FlexiSoftness><FlexiTension>0</FlexiTension><FlexiDrag>0</FlexiDrag><FlexiGravity>0</FlexiGravity><FlexiWind>0</FlexiWind><FlexiForceX>0</FlexiForceX><FlexiForceY>0</FlexiForceY><FlexiForceZ>0</FlexiForceZ><LightColorR>0</LightColorR><LightColorG>0</LightColorG><LightColorB>0</LightColorB><LightColorA>1</LightColorA><LightRadius>0</LightRadius><LightCutoff>0</LightCutoff><LightFalloff>0</LightFalloff><LightIntensity>1</LightIntensity><FlexiEntry>false</FlexiEntry><LightEntry>false</LightEntry><SculptEntry>false</SculptEntry></Shape><Scale><X>5</X><Y>5</Y><Z>0.2</Z></Scale><UpdateFlag>0</UpdateFlag><SitTargetOrientation><X>0</X><Y>0</Y><Z>0</Z><W>1</W></SitTargetOrientation><SitTargetPosition><X>0</X><Y>0</Y><Z>0</Z></SitTargetPosition><SitTargetPositionLL><X>0</X><Y>0</Y><Z>0</Z></SitTargetPositionLL><SitTargetOrientationLL><X>0</X><Y>0</Y><Z>0</Z><W>1</W></SitTargetOrientationLL><ParentID>1269920860</ParentID><CreationDate>1258746394</CreationDate><Category>0</Category><SalePrice>10</SalePrice><ObjectSaleType>0</ObjectSaleType><OwnershipCost>0</OwnershipCost><GroupID><Guid>19b9cf50-f667-4a97-806b-fec7d4363c46</Guid></GroupID><OwnerID><Guid>155adad4-8975-4706-b95f-fa75af0678c5</Guid></OwnerID><LastOwnerID><Guid>155adad4-8975-4706-b95f-fa75af0678c5</Guid></LastOwnerID><BaseMask>581632</BaseMask><OwnerMask>581632</OwnerMask><GroupMask>0</GroupMask><EveryoneMask>0</EveryoneMask><NextOwnerMask>581632</NextOwnerMask><Flags>None</Flags><CollisionSound><Guid>00000000-0000-0000-0000-000000000000</Guid></CollisionSound><CollisionSoundVolume>0</CollisionSoundVolume></SceneObjectPart><SceneObjectPart xmlns:xsi="http://www.w3.org/2001/XMLSchema-instance" xmlns:xsd="http://www.w3.org/2001/XMLSchema"><AllowedDrop>false</AllowedDrop><CreatorID><Guid>155adad4-8975-4706-b95f-fa75af0678c5</Guid></CreatorID><FolderID><Guid>eab31a1d-37ac-4e64-84e4-3e620caf82a0</Guid></FolderID><InventorySerial>1</InventorySerial><TaskInventory /><ObjectFlags>0</ObjectFlags><UUID><Guid>eab31a1d-37ac-4e64-84e4-3e620caf82a0</Guid></UUID><LocalId>1269920863</LocalId><Name>cz OV floor</Name><Material>3</Material><PassTouches>false</PassTouches><RegionHandle>1099511628032000</RegionHandle><ScriptAccessPin>0</ScriptAccessPin><PlaySoundSlavePrims /><LoopSoundSlavePrims /><GroupPosition><X>76</X><Y>88</Y><Z>21.75</Z></GroupPosition><OffsetPosition><X>1.71191346E-06</X><Y>8</Y><Z>1.91035213E-07</Z></OffsetPosition><RotationOffset><X>1.07832493E-15</X><Y>-8.99543135E-13</Y><Z>9.158721E-13</Z><W>0.99999994</W></RotationOffset><Velocity><X>0</X><Y>0</Y><Z>0</Z></Velocity><AngularVelocity><X>0</X><Y>0</Y><Z>0</Z></AngularVelocity><Acceleration><X>0</X><Y>0</Y><Z>0</Z></Acceleration><Description /><Color /><Text /><SitName /><TouchName /><LinkNum>4</LinkNum><ClickAction>0</ClickAction><Shape><ProfileCurve>1</ProfileCurve><TextureEntry>xzptR3TPRgyWH/Ttp1ZR9gFW7bXCh+ZFrbMlxc0ZJYuVAAAAAAAAAAAAQAAAAABAAAAAAAAAAAAAAMABAAAAAAA=</TextureEntry><ExtraParams>AA==</ExtraParams><PathBegin>0</PathBegin><PathCurve>16</PathCurve><PathEnd>0</PathEnd><PathRadiusOffset>0</PathRadiusOffset><PathRevolutions>0</PathRevolutions><PathScaleX>100</PathScaleX><PathScaleY>100</PathScaleY><PathShearX>0</PathShearX><PathShearY>0</PathShearY><PathSkew>0</PathSkew><PathTaperX>0</PathTaperX><PathTaperY>0</PathTaperY><PathTwist>0</PathTwist><PathTwistBegin>0</PathTwistBegin><PCode>9</PCode><ProfileBegin>0</ProfileBegin><ProfileEnd>0</ProfileEnd><ProfileHollow>0</ProfileHollow><Scale><X>5</X><Y>8</Y><Z>0.2</Z></Scale><State>0</State><ProfileShape>Square</ProfileShape><HollowShape>Same</HollowShape><SculptTexture><Guid>00000000-0000-0000-0000-000000000000</Guid></SculptTexture><SculptType>0</SculptType><SculptData /><FlexiSoftness>0</FlexiSoftness><FlexiTension>0</FlexiTension><FlexiDrag>0</FlexiDrag><FlexiGravity>0</FlexiGravity><FlexiWind>0</FlexiWind><FlexiForceX>0</FlexiForceX><FlexiForceY>0</FlexiForceY><FlexiForceZ>0</FlexiForceZ><LightColorR>0</LightColorR><LightColorG>0</LightColorG><LightColorB>0</LightColorB><LightColorA>1</LightColorA><LightRadius>0</LightRadius><LightCutoff>0</LightCutoff><LightFalloff>0</LightFalloff><LightIntensity>1</LightIntensity><FlexiEntry>false</FlexiEntry><LightEntry>false</LightEntry><SculptEntry>false</SculptEntry></Shape><Scale><X>5</X><Y>8</Y><Z>0.2</Z></Scale><UpdateFlag>0</UpdateFlag><SitTargetOrientation><X>0</X><Y>0</Y><Z>0</Z><W>1</W></SitTargetOrientation><SitTargetPosition><X>0</X><Y>0</Y><Z>0</Z></SitTargetPosition><SitTargetPositionLL><X>0</X><Y>0</Y><Z>0</Z></SitTargetPositionLL><SitTargetOrientationLL><X>0</X><Y>0</Y><Z>0</Z><W>1</W></SitTargetOrientationLL><ParentID>1269920860</ParentID><CreationDate>1258746394</CreationDate><Category>0</Category><SalePrice>10</SalePrice><ObjectSaleType>0</ObjectSaleType><OwnershipCost>0</OwnershipCost><GroupID><Guid>19b9cf50-f667-4a97-806b-fec7d4363c46</Guid></GroupID><OwnerID><Guid>155adad4-8975-4706-b95f-fa75af0678c5</Guid></OwnerID><LastOwnerID><Guid>155adad4-8975-4706-b95f-fa75af0678c5</Guid></LastOwnerID><BaseMask>581632</BaseMask><OwnerMask>581632</OwnerMask><GroupMask>0</GroupMask><EveryoneMask>0</EveryoneMask><NextOwnerMask>581632</NextOwnerMask><Flags>None</Flags><CollisionSound><Guid>00000000-0000-0000-0000-000000000000</Guid></CollisionSound><CollisionSoundVolume>0</CollisionSoundVolume></SceneObjectPart><SceneObjectPart xmlns:xsi="http://www.w3.org/2001/XMLSchema-instance" xmlns:xsd="http://www.w3.org/2001/XMLSchema"><AllowedDrop>false</AllowedDrop><CreatorID><Guid>155adad4-8975-4706-b95f-fa75af0678c5</Guid></CreatorID><FolderID><Guid>377078c5-2bbe-45f6-ba66-07726a32feb0</Guid></FolderID><InventorySerial>1</InventorySerial><TaskInventory /><ObjectFlags>0</ObjectFlags><UUID><Guid>377078c5-2bbe-45f6-ba66-07726a32feb0</Guid></UUID><LocalId>1269920864</LocalId><Name>planter</Name><Material>3</Material><PassTouches>false</PassTouches><RegionHandle>1099511628032000</RegionHandle><ScriptAccessPin>0</ScriptAccessPin><PlaySoundSlavePrims /><LoopSoundSlavePrims /><GroupPosition><X>76</X><Y>88</Y><Z>21.75</Z></GroupPosition><OffsetPosition><X>2.77875273E-07</X><Y>-14.863327</Y><Z>-3.54820656E-07</Z></OffsetPosition><RotationOffset><X>1.07832493E-15</X><Y>-8.99543135E-13</Y><Z>9.158721E-13</Z><W>0.99999994</W></RotationOffset><Velocity><X>0</X><Y>0</Y><Z>0</Z></Velocity><AngularVelocity><X>0</X><Y>0</Y><Z>0</Z></AngularVelocity><Acceleration><X>0</X><Y>0</Y><Z>0</Z></Acceleration><Description /><Color /><Text /><SitName /><TouchName /><LinkNum>5</LinkNum><ClickAction>0</ClickAction><Shape><ProfileCurve>1</ProfileCurve><TextureEntry>xzptR3TPRgyWH/Ttp1ZR9gFW7bXCh+ZFrbMlxc0ZJYuVAAAAAAAAAAAAQAAAAIA/ADJzAAAAAAAAAMABAAAAAAA=</TextureEntry><ExtraParams>AA==</ExtraParams><PathBegin>0</PathBegin><PathCurve>16</PathCurve><PathEnd>0</PathEnd><PathRadiusOffset>0</PathRadiusOffset><PathRevolutions>0</PathRevolutions><PathScaleX>100</PathScaleX><PathScaleY>100</PathScaleY><PathShearX>0</PathShearX><PathShearY>0</PathShearY><PathSkew>0</PathSkew><PathTaperX>0</PathTaperX><PathTaperY>0</PathTaperY><PathTwist>0</PathTwist><PathTwistBegin>0</PathTwistBegin><PCode>9</PCode><ProfileBegin>25000</ProfileBegin><ProfileEnd>0</ProfileEnd><ProfileHollow>0</ProfileHollow><Scale><X>5</X><Y>5.725357</Y><Z>0.2</Z></Scale><State>0</State><ProfileShape>Square</ProfileShape><HollowShape>Same</HollowShape><SculptTexture><Guid>00000000-0000-0000-0000-000000000000</Guid></SculptTexture><SculptType>0</SculptType><SculptData /><FlexiSoftness>0</FlexiSoftness><FlexiTension>0</FlexiTension><FlexiDrag>0</FlexiDrag><FlexiGravity>0</FlexiGravity><FlexiWind>0</FlexiWind><FlexiForceX>0</FlexiForceX><FlexiForceY>0</FlexiForceY><FlexiForceZ>0</FlexiForceZ><LightColorR>0</LightColorR><LightColorG>0</LightColorG><LightColorB>0</LightColorB><LightColorA>1</LightColorA><LightRadius>0</LightRadius><LightCutoff>0</LightCutoff><LightFalloff>0</LightFalloff><LightIntensity>1</LightIntensity><FlexiEntry>false</FlexiEntry><LightEntry>false</LightEntry><SculptEntry>false</SculptEntry></Shape><Scale><X>5</X><Y>5.725357</Y><Z>0.2</Z></Scale><UpdateFlag>0</UpdateFlag><SitTargetOrientation><X>0</X><Y>0</Y><Z>0</Z><W>1</W></SitTargetOrientation><SitTargetPosition><X>0</X><Y>0</Y><Z>0</Z></SitTargetPosition><SitTargetPositionLL><X>0</X><Y>0</Y><Z>0</Z></SitTargetPositionLL><SitTargetOrientationLL><X>0</X><Y>0</Y><Z>0</Z><W>1</W></SitTargetOrientationLL><ParentID>1269920860</ParentID><CreationDate>1258746394</CreationDate><Category>0</Category><SalePrice>10</SalePrice><ObjectSaleType>0</ObjectSaleType><OwnershipCost>0</OwnershipCost><GroupID><Guid>19b9cf50-f667-4a97-806b-fec7d4363c46</Guid></GroupID><OwnerID><Guid>155adad4-8975-4706-b95f-fa75af0678c5</Guid></OwnerID><LastOwnerID><Guid>155adad4-8975-4706-b95f-fa75af0678c5</Guid></LastOwnerID><BaseMask>581632</BaseMask><OwnerMask>581632</OwnerMask><GroupMask>0</GroupMask><EveryoneMask>0</EveryoneMask><NextOwnerMask>581632</NextOwnerMask><Flags>None</Flags><CollisionSound><Guid>00000000-0000-0000-0000-000000000000</Guid></CollisionSound><CollisionSoundVolume>0</CollisionSoundVolume></SceneObjectPart><SceneObjectPart xmlns:xsi="http://www.w3.org/2001/XMLSchema-instance" xmlns:xsd="http://www.w3.org/2001/XMLSchema"><AllowedDrop>false</AllowedDrop><CreatorID><Guid>155adad4-8975-4706-b95f-fa75af0678c5</Guid></CreatorID><FolderID><Guid>3117dc2c-d546-4ad2-86ae-98090c1a2226</Guid></FolderID><InventorySerial>1</InventorySerial><TaskInventory /><ObjectFlags>0</ObjectFlags><UUID><Guid>3117dc2c-d546-4ad2-86ae-98090c1a2226</Guid></UUID><LocalId>1269920865</LocalId><Name>cz OV floor</Name><Material>3</Material><PassTouches>false</PassTouches><RegionHandle>1099511628032000</RegionHandle><ScriptAccessPin>0</ScriptAccessPin><PlaySoundSlavePrims /><LoopSoundSlavePrims /><GroupPosition><X>76</X><Y>88</Y><Z>21.75</Z></GroupPosition><OffsetPosition><X>-1.71237582E-06</X><Y>-7.99998474</Y><Z>-1.91034857E-07</Z></OffsetPosition><RotationOffset><X>-3.06114423E-08</X><Y>-6.74351668E-07</Y><Z>-8.4292445E-08</Z><W>0.99999994</W></RotationOffset><Velocity><X>0</X><Y>0</Y><Z>0</Z></Velocity><AngularVelocity><X>0</X><Y>0</Y><Z>0</Z></AngularVelocity><Acceleration><X>0</X><Y>0</Y><Z>0</Z></Acceleration><Description /><Color /><Text /><SitName /><TouchName /><LinkNum>6</LinkNum><ClickAction>0</ClickAction><Shape><ProfileCurve>1</ProfileCurve><TextureEntry>xzptR3TPRgyWH/Ttp1ZR9gFW7bXCh+ZFrbMlxc0ZJYuVAAAAAAAAAAAAQAAAAABAAAAAAAAAAAAAAMABAAAAAAA=</TextureEntry><ExtraParams>AA==</ExtraParams><PathBegin>0</PathBegin><PathCurve>16</PathCurve><PathEnd>0</PathEnd><PathRadiusOffset>0</PathRadiusOffset><PathRevolutions>0</PathRevolutions><PathScaleX>100</PathScaleX><PathScaleY>100</PathScaleY><PathShearX>0</PathShearX><PathShearY>0</PathShearY><PathSkew>0</PathSkew><PathTaperX>0</PathTaperX><PathTaperY>0</PathTaperY><PathTwist>0</PathTwist><PathTwistBegin>0</PathTwistBegin><PCode>9</PCode><ProfileBegin>0</ProfileBegin><ProfileEnd>0</ProfileEnd><ProfileHollow>0</ProfileHollow><Scale><X>5</X><Y>8</Y><Z>0.2</Z></Scale><State>0</State><ProfileShape>Square</ProfileShape><HollowShape>Same</HollowShape><SculptTexture><Guid>00000000-0000-0000-0000-000000000000</Guid></SculptTexture><SculptType>0</SculptType><SculptData /><FlexiSoftness>0</FlexiSoftness><FlexiTension>0</FlexiTension><FlexiDrag>0</FlexiDrag><FlexiGravity>0</FlexiGravity><FlexiWind>0</FlexiWind><FlexiForceX>0</FlexiForceX><FlexiForceY>0</FlexiForceY><FlexiForceZ>0</FlexiForceZ><LightColorR>0</LightColorR><LightColorG>0</LightColorG><LightColorB>0</LightColorB><LightColorA>1</LightColorA><LightRadius>0</LightRadius><LightCutoff>0</LightCutoff><LightFalloff>0</LightFalloff><LightIntensity>1</LightIntensity><FlexiEntry>false</FlexiEntry><LightEntry>false</LightEntry><SculptEntry>false</SculptEntry></Shape><Scale><X>5</X><Y>8</Y><Z>0.2</Z></Scale><UpdateFlag>0</UpdateFlag><SitTargetOrientation><X>0</X><Y>0</Y><Z>0</Z><W>1</W></SitTargetOrientation><SitTargetPosition><X>0</X><Y>0</Y><Z>0</Z></SitTargetPosition><SitTargetPositionLL><X>0</X><Y>0</Y><Z>0</Z></SitTargetPositionLL><SitTargetOrientationLL><X>0</X><Y>0</Y><Z>0</Z><W>1</W></SitTargetOrientationLL><ParentID>1269920860</ParentID><CreationDate>1258746394</CreationDate><Category>0</Category><SalePrice>10</SalePrice><ObjectSaleType>0</ObjectSaleType><OwnershipCost>0</OwnershipCost><GroupID><Guid>19b9cf50-f667-4a97-806b-fec7d4363c46</Guid></GroupID><OwnerID><Guid>155adad4-8975-4706-b95f-fa75af0678c5</Guid></OwnerID><LastOwnerID><Guid>155adad4-8975-4706-b95f-fa75af0678c5</Guid></LastOwnerID><BaseMask>581632</BaseMask><OwnerMask>581632</OwnerMask><GroupMask>0</GroupMask><EveryoneMask>0</EveryoneMask><NextOwnerMask>581632</NextOwnerMask><Flags>None</Flags><CollisionSound><Guid>00000000-0000-0000-0000-000000000000</Guid></CollisionSound><CollisionSoundVolume>0</CollisionSoundVolume></SceneObjectPart><SceneObjectPart xmlns:xsi="http://www.w3.org/2001/XMLSchema-instance" xmlns:xsd="http://www.w3.org/2001/XMLSchema"><AllowedDrop>false</AllowedDrop><CreatorID><Guid>155adad4-8975-4706-b95f-fa75af0678c5</Guid></CreatorID><FolderID><Guid>2c1040b6-7f72-45ab-b274-ae7142e44de5</Guid></FolderID><InventorySerial>1</InventorySerial><TaskInventory /><ObjectFlags>0</ObjectFlags><UUID><Guid>2c1040b6-7f72-45ab-b274-ae7142e44de5</Guid></UUID><LocalId>1269920866</LocalId><Name>block</Name><Material>3</Material><PassTouches>false</PassTouches><RegionHandle>1099511628032000</RegionHandle><ScriptAccessPin>0</ScriptAccessPin><PlaySoundSlavePrims /><LoopSoundSlavePrims /><GroupPosition><X>76</X><Y>88</Y><Z>21.75</Z></GroupPosition><OffsetPosition><X>2.51277566</X><Y>13.4055634</Y><Z>-0.6831497</Z></OffsetPosition><RotationOffset><X>1.06906E-05</X><Y>-0.7071177</Y><Z>1.07583446E-05</Z><W>0.707095861</W></RotationOffset><Velocity><X>0</X><Y>0</Y><Z>0</Z></Velocity><AngularVelocity><X>0</X><Y>0</Y><Z>0</Z></AngularVelocity><Acceleration><X>0</X><Y>0</Y><Z>0</Z></Acceleration><Description /><Color /><Text /><SitName /><TouchName /><LinkNum>7</LinkNum><ClickAction>0</ClickAction><Shape><ProfileCurve>1</ProfileCurve><TextureEntry>xzptR3TPRgyWH/Ttp1ZR9gAAAAAAAAAAgD8AAACAPwAAAAAAAAAAAADAAAAAAA==</TextureEntry><ExtraParams>AA==</ExtraParams><PathBegin>0</PathBegin><PathCurve>16</PathCurve><PathEnd>0</PathEnd><PathRadiusOffset>0</PathRadiusOffset><PathRevolutions>0</PathRevolutions><PathScaleX>100</PathScaleX><PathScaleY>112</PathScaleY><PathShearX>0</PathShearX><PathShearY>250</PathShearY><PathSkew>0</PathSkew><PathTaperX>0</PathTaperX><PathTaperY>0</PathTaperY><PathTwist>0</PathTwist><PathTwistBegin>0</PathTwistBegin><PCode>9</PCode><ProfileBegin>0</ProfileBegin><ProfileEnd>0</ProfileEnd><ProfileHollow>0</ProfileHollow><Scale><X>2</X><Y>8</Y><Z>1</Z></Scale><State>0</State><ProfileShape>Square</ProfileShape><HollowShape>Same</HollowShape><SculptTexture><Guid>00000000-0000-0000-0000-000000000000</Guid></SculptTexture><SculptType>0</SculptType><SculptData /><FlexiSoftness>0</FlexiSoftness><FlexiTension>0</FlexiTension><FlexiDrag>0</FlexiDrag><FlexiGravity>0</FlexiGravity><FlexiWind>0</FlexiWind><FlexiForceX>0</FlexiForceX><FlexiForceY>0</FlexiForceY><FlexiForceZ>0</FlexiForceZ><LightColorR>0</LightColorR><LightColorG>0</LightColorG><LightColorB>0</LightColorB><LightColorA>1</LightColorA><LightRadius>0</LightRadius><LightCutoff>0</LightCutoff><LightFalloff>0</LightFalloff><LightIntensity>1</LightIntensity><FlexiEntry>false</FlexiEntry><LightEntry>false</LightEntry><SculptEntry>false</SculptEntry></Shape><Scale><X>2</X><Y>8</Y><Z>1</Z></Scale><UpdateFlag>0</UpdateFlag><SitTargetOrientation><X>0</X><Y>0</Y><Z>0</Z><W>1</W></SitTargetOrientation><SitTargetPosition><X>0</X><Y>0</Y><Z>0</Z></SitTargetPosition><SitTargetPositionLL><X>0</X><Y>0</Y><Z>0</Z></SitTargetPositionLL><SitTargetOrientationLL><X>0</X><Y>0</Y><Z>0</Z><W>1</W></SitTargetOrientationLL><ParentID>1269920860</ParentID><CreationDate>1258746394</CreationDate><Category>0</Category><SalePrice>10</SalePrice><ObjectSaleType>0</ObjectSaleType><OwnershipCost>0</OwnershipCost><GroupID><Guid>19b9cf50-f667-4a97-806b-fec7d4363c46</Guid></GroupID><OwnerID><Guid>155adad4-8975-4706-b95f-fa75af0678c5</Guid></OwnerID><LastOwnerID><Guid>155adad4-8975-4706-b95f-fa75af0678c5</Guid></LastOwnerID><BaseMask>581632</BaseMask><OwnerMask>581632</OwnerMask><GroupMask>0</GroupMask><EveryoneMask>0</EveryoneMask><NextOwnerMask>581632</NextOwnerMask><Flags>None</Flags><CollisionSound><Guid>00000000-0000-0000-0000-000000000000</Guid></CollisionSound><CollisionSoundVolume>0</CollisionSoundVolume></SceneObjectPart><SceneObjectPart xmlns:xsi="http://www.w3.org/2001/XMLSchema-instance" xmlns:xsd="http://www.w3.org/2001/XMLSchema"><AllowedDrop>false</AllowedDrop><CreatorID><Guid>155adad4-8975-4706-b95f-fa75af0678c5</Guid></CreatorID><FolderID><Guid>c3515cdb-a105-440b-aff3-9ce978682237</Guid></FolderID><InventorySerial>1</InventorySerial><TaskInventory /><ObjectFlags>0</ObjectFlags><UUID><Guid>c3515cdb-a105-440b-aff3-9ce978682237</Guid></UUID><LocalId>1269920867</LocalId><Name>block</Name><Material>3</Material><PassTouches>false</PassTouches><RegionHandle>1099511628032000</RegionHandle><ScriptAccessPin>0</ScriptAccessPin><PlaySoundSlavePrims /><LoopSoundSlavePrims /><GroupPosition><X>76</X><Y>88</Y><Z>21.75</Z></GroupPosition><OffsetPosition><X>2.51277375</X><Y>5.4059906</Y><Z>-0.6831499</Z></OffsetPosition><RotationOffset><X>1.06906E-05</X><Y>-0.7071177</Y><Z>1.07583446E-05</Z><W>0.707095861</W></RotationOffset><Velocity><X>0</X><Y>0</Y><Z>0</Z></Velocity><AngularVelocity><X>0</X><Y>0</Y><Z>0</Z></AngularVelocity><Acceleration><X>0</X><Y>0</Y><Z>0</Z></Acceleration><Description /><Color /><Text /><SitName /><TouchName /><LinkNum>8</LinkNum><ClickAction>0</ClickAction><Shape><ProfileCurve>1</ProfileCurve><TextureEntry>xzptR3TPRgyWH/Ttp1ZR9gAAAAAAAAAAgD8AAACAPwAAAAAAAAAAAADAAAAAAA==</TextureEntry><ExtraParams>AA==</ExtraParams><PathBegin>0</PathBegin><PathCurve>16</PathCurve><PathEnd>0</PathEnd><PathRadiusOffset>0</PathRadiusOffset><PathRevolutions>0</PathRevolutions><PathScaleX>100</PathScaleX><PathScaleY>100</PathScaleY><PathShearX>0</PathShearX><PathShearY>0</PathShearY><PathSkew>0</PathSkew><PathTaperX>0</PathTaperX><PathTaperY>0</PathTaperY><PathTwist>0</PathTwist><PathTwistBegin>0</PathTwistBegin><PCode>9</PCode><ProfileBegin>0</ProfileBegin><ProfileEnd>0</ProfileEnd><ProfileHollow>0</ProfileHollow><Scale><X>2</X><Y>8</Y><Z>1</Z></Scale><State>0</State><ProfileShape>Square</ProfileShape><HollowShape>Same</HollowShape><SculptTexture><Guid>00000000-0000-0000-0000-000000000000</Guid></SculptTexture><SculptType>0</SculptType><SculptData /><FlexiSoftness>0</FlexiSoftness><FlexiTension>0</FlexiTension><FlexiDrag>0</FlexiDrag><FlexiGravity>0</FlexiGravity><FlexiWind>0</FlexiWind><FlexiForceX>0</FlexiForceX><FlexiForceY>0</FlexiForceY><FlexiForceZ>0</FlexiForceZ><LightColorR>0</LightColorR><LightColorG>0</LightColorG><LightColorB>0</LightColorB><LightColorA>1</LightColorA><LightRadius>0</LightRadius><LightCutoff>0</LightCutoff><LightFalloff>0</LightFalloff><LightIntensity>1</LightIntensity><FlexiEntry>false</FlexiEntry><LightEntry>false</LightEntry><SculptEntry>false</SculptEntry></Shape><Scale><X>2</X><Y>8</Y><Z>1</Z></Scale><UpdateFlag>0</UpdateFlag><SitTargetOrientation><X>0</X><Y>0</Y><Z>0</Z><W>1</W></SitTargetOrientation><SitTargetPosition><X>0</X><Y>0</Y><Z>0</Z></SitTargetPosition><SitTargetPositionLL><X>0</X><Y>0</Y><Z>0</Z></SitTargetPositionLL><SitTargetOrientationLL><X>0</X><Y>0</Y><Z>0</Z><W>1</W></SitTargetOrientationLL><ParentID>1269920860</ParentID><CreationDate>1258746394</CreationDate><Category>0</Category><SalePrice>10</SalePrice><ObjectSaleType>0</ObjectSaleType><OwnershipCost>0</OwnershipCost><GroupID><Guid>19b9cf50-f667-4a97-806b-fec7d4363c46</Guid></GroupID><OwnerID><Guid>155adad4-8975-4706-b95f-fa75af0678c5</Guid></OwnerID><LastOwnerID><Guid>155adad4-8975-4706-b95f-fa75af0678c5</Guid></LastOwnerID><BaseMask>581632</BaseMask><OwnerMask>581632</OwnerMask><GroupMask>0</GroupMask><EveryoneMask>0</EveryoneMask><NextOwnerMask>581632</NextOwnerMask><Flags>None</Flags><CollisionSound><Guid>00000000-0000-0000-0000-000000000000</Guid></CollisionSound><CollisionSoundVolume>0</CollisionSoundVolume></SceneObjectPart><SceneObjectPart xmlns:xsi="http://www.w3.org/2001/XMLSchema-instance" xmlns:xsd="http://www.w3.org/2001/XMLSchema"><AllowedDrop>false</AllowedDrop><CreatorID><Guid>155adad4-8975-4706-b95f-fa75af0678c5</Guid></CreatorID><FolderID><Guid>3baeb971-0a72-4c9e-b543-abc40126c11a</Guid></FolderID><InventorySerial>1</InventorySerial><TaskInventory /><ObjectFlags>0</ObjectFlags><UUID><Guid>3baeb971-0a72-4c9e-b543-abc40126c11a</Guid></UUID><LocalId>1269920868</LocalId><Name>block</Name><Material>3</Material><PassTouches>false</PassTouches><RegionHandle>1099511628032000</RegionHandle><ScriptAccessPin>0</ScriptAccessPin><PlaySoundSlavePrims /><LoopSoundSlavePrims /><GroupPosition><X>76</X><Y>88</Y><Z>21.75</Z></GroupPosition><OffsetPosition><X>2.512772</X><Y>-2.59400964</Y><Z>-0.683150053</Z></OffsetPosition><RotationOffset><X>1.06906E-05</X><Y>-0.7071177</Y><Z>1.07583446E-05</Z><W>0.707095861</W></RotationOffset><Velocity><X>0</X><Y>0</Y><Z>0</Z></Velocity><AngularVelocity><X>0</X><Y>0</Y><Z>0</Z></AngularVelocity><Acceleration><X>0</X><Y>0</Y><Z>0</Z></Acceleration><Description /><Color /><Text /><SitName /><TouchName /><LinkNum>9</LinkNum><ClickAction>0</ClickAction><Shape><ProfileCurve>1</ProfileCurve><TextureEntry>xzptR3TPRgyWH/Ttp1ZR9gAAAAAAAAAAgD8AAACAPwAAAAAAAAAAAADAAAAAAA==</TextureEntry><ExtraParams>AA==</ExtraParams><PathBegin>0</PathBegin><PathCurve>16</PathCurve><PathEnd>0</PathEnd><PathRadiusOffset>0</PathRadiusOffset><PathRevolutions>0</PathRevolutions><PathScaleX>100</PathScaleX><PathScaleY>100</PathScaleY><PathShearX>0</PathShearX><PathShearY>0</PathShearY><PathSkew>0</PathSkew><PathTaperX>0</PathTaperX><PathTaperY>0</PathTaperY><PathTwist>0</PathTwist><PathTwistBegin>0</PathTwistBegin><PCode>9</PCode><ProfileBegin>0</ProfileBegin><ProfileEnd>0</ProfileEnd><ProfileHollow>0</ProfileHollow><Scale><X>2</X><Y>8</Y><Z>1</Z></Scale><State>0</State><ProfileShape>Square</ProfileShape><HollowShape>Same</HollowShape><SculptTexture><Guid>00000000-0000-0000-0000-000000000000</Guid></SculptTexture><SculptType>0</SculptType><SculptData /><FlexiSoftness>0</FlexiSoftness><FlexiTension>0</FlexiTension><FlexiDrag>0</FlexiDrag><FlexiGravity>0</FlexiGravity><FlexiWind>0</FlexiWind><FlexiForceX>0</FlexiForceX><FlexiForceY>0</FlexiForceY><FlexiForceZ>0</FlexiForceZ><LightColorR>0</LightColorR><LightColorG>0</LightColorG><LightColorB>0</LightColorB><LightColorA>1</LightColorA><LightRadius>0</LightRadius><LightCutoff>0</LightCutoff><LightFalloff>0</LightFalloff><LightIntensity>1</LightIntensity><FlexiEntry>false</FlexiEntry><LightEntry>false</LightEntry><SculptEntry>false</SculptEntry></Shape><Scale><X>2</X><Y>8</Y><Z>1</Z></Scale><UpdateFlag>0</UpdateFlag><SitTargetOrientation><X>0</X><Y>0</Y><Z>0</Z><W>1</W></SitTargetOrientation><SitTargetPosition><X>0</X><Y>0</Y><Z>0</Z></SitTargetPosition><SitTargetPositionLL><X>0</X><Y>0</Y><Z>0</Z></SitTargetPositionLL><SitTargetOrientationLL><X>0</X><Y>0</Y><Z>0</Z><W>1</W></SitTargetOrientationLL><ParentID>1269920860</ParentID><CreationDate>1258746394</CreationDate><Category>0</Category><SalePrice>10</SalePrice><ObjectSaleType>0</ObjectSaleType><OwnershipCost>0</OwnershipCost><GroupID><Guid>19b9cf50-f667-4a97-806b-fec7d4363c46</Guid></GroupID><OwnerID><Guid>155adad4-8975-4706-b95f-fa75af0678c5</Guid></OwnerID><LastOwnerID><Guid>155adad4-8975-4706-b95f-fa75af0678c5</Guid></LastOwnerID><BaseMask>581632</BaseMask><OwnerMask>581632</OwnerMask><GroupMask>0</GroupMask><EveryoneMask>0</EveryoneMask><NextOwnerMask>581632</NextOwnerMask><Flags>None</Flags><CollisionSound><Guid>00000000-0000-0000-0000-000000000000</Guid></CollisionSound><CollisionSoundVolume>0</CollisionSoundVolume></SceneObjectPart><SceneObjectPart xmlns:xsi="http://www.w3.org/2001/XMLSchema-instance" xmlns:xsd="http://www.w3.org/2001/XMLSchema"><AllowedDrop>false</AllowedDrop><CreatorID><Guid>155adad4-8975-4706-b95f-fa75af0678c5</Guid></CreatorID><FolderID><Guid>b9a5c2f7-717b-494e-952a-04e49f7be20b</Guid></FolderID><InventorySerial>1</InventorySerial><TaskInventory /><ObjectFlags>0</ObjectFlags><UUID><Guid>b9a5c2f7-717b-494e-952a-04e49f7be20b</Guid></UUID><LocalId>1269920869</LocalId><Name>block</Name><Material>3</Material><PassTouches>false</PassTouches><RegionHandle>1099511628032000</RegionHandle><ScriptAccessPin>0</ScriptAccessPin><PlaySoundSlavePrims /><LoopSoundSlavePrims /><GroupPosition><X>76</X><Y>88</Y><Z>21.75</Z></GroupPosition><OffsetPosition><X>2.51276445</X><Y>-9.645752</Y><Z>-0.6833944</Z></OffsetPosition><RotationOffset><X>1.06906E-05</X><Y>-0.7071177</Y><Z>1.07583446E-05</Z><W>0.707095861</W></RotationOffset><Velocity><X>0</X><Y>0</Y><Z>0</Z></Velocity><AngularVelocity><X>0</X><Y>0</Y><Z>0</Z></AngularVelocity><Acceleration><X>0</X><Y>0</Y><Z>0</Z></Acceleration><Description /><Color /><Text /><SitName /><TouchName /><LinkNum>10</LinkNum><ClickAction>0</ClickAction><Shape><ProfileCurve>1</ProfileCurve><TextureEntry>xzptR3TPRgyWH/Ttp1ZR9gAAAAAAAAAAgD8EQLuzPhBAu7M+AEC7sz4CAACAPwQAAIA/CAAAgD8QAACAPwAAAAAAAAAAAADAAAAAAA==</TextureEntry><ExtraParams>AA==</ExtraParams><PathBegin>0</PathBegin><PathCurve>16</PathCurve><PathEnd>0</PathEnd><PathRadiusOffset>0</PathRadiusOffset><PathRevolutions>0</PathRevolutions><PathScaleX>100</PathScaleX><PathScaleY>100</PathScaleY><PathShearX>0</PathShearX><PathShearY>0</PathShearY><PathSkew>0</PathSkew><PathTaperX>0</PathTaperX><PathTaperY>0</PathTaperY><PathTwist>0</PathTwist><PathTwistBegin>0</PathTwistBegin><PCode>9</PCode><ProfileBegin>0</ProfileBegin><ProfileEnd>0</ProfileEnd><ProfileHollow>0</ProfileHollow><Scale><X>2</X><Y>6.11716461</Y><Z>1</Z></Scale><State>0</State><ProfileShape>Square</ProfileShape><HollowShape>Same</HollowShape><SculptTexture><Guid>00000000-0000-0000-0000-000000000000</Guid></SculptTexture><SculptType>0</SculptType><SculptData /><FlexiSoftness>0</FlexiSoftness><FlexiTension>0</FlexiTension><FlexiDrag>0</FlexiDrag><FlexiGravity>0</FlexiGravity><FlexiWind>0</FlexiWind><FlexiForceX>0</FlexiForceX><FlexiForceY>0</FlexiForceY><FlexiForceZ>0</FlexiForceZ><LightColorR>0</LightColorR><LightColorG>0</LightColorG><LightColorB>0</LightColorB><LightColorA>1</LightColorA><LightRadius>0</LightRadius><LightCutoff>0</LightCutoff><LightFalloff>0</LightFalloff><LightIntensity>1</LightIntensity><FlexiEntry>false</FlexiEntry><LightEntry>false</LightEntry><SculptEntry>false</SculptEntry></Shape><Scale><X>2</X><Y>6.11716461</Y><Z>1</Z></Scale><UpdateFlag>0</UpdateFlag><SitTargetOrientation><X>0</X><Y>0</Y><Z>0</Z><W>1</W></SitTargetOrientation><SitTargetPosition><X>0</X><Y>0</Y><Z>0</Z></SitTargetPosition><SitTargetPositionLL><X>0</X><Y>0</Y><Z>0</Z></SitTargetPositionLL><SitTargetOrientationLL><X>0</X><Y>0</Y><Z>0</Z><W>1</W></SitTargetOrientationLL><ParentID>1269920860</ParentID><CreationDate>1258746394</CreationDate><Category>0</Category><SalePrice>10</SalePrice><ObjectSaleType>0</ObjectSaleType><OwnershipCost>0</OwnershipCost><GroupID><Guid>19b9cf50-f667-4a97-806b-fec7d4363c46</Guid></GroupID><OwnerID><Guid>155adad4-8975-4706-b95f-fa75af0678c5</Guid></OwnerID><LastOwnerID><Guid>155adad4-8975-4706-b95f-fa75af0678c5</Guid></LastOwnerID><BaseMask>581632</BaseMask><OwnerMask>581632</OwnerMask><GroupMask>0</GroupMask><EveryoneMask>0</EveryoneMask><NextOwnerMask>581632</NextOwnerMask><Flags>None</Flags><CollisionSound><Guid>00000000-0000-0000-0000-000000000000</Guid></CollisionSound><CollisionSoundVolume>0</CollisionSoundVolume></SceneObjectPart><SceneObjectPart xmlns:xsi="http://www.w3.org/2001/XMLSchema-instance" xmlns:xsd="http://www.w3.org/2001/XMLSchema"><AllowedDrop>false</AllowedDrop><CreatorID><Guid>155adad4-8975-4706-b95f-fa75af0678c5</Guid></CreatorID><FolderID><Guid>10542a38-5b37-4568-b774-7f5f0d8211b8</Guid></FolderID><InventorySerial>1</InventorySerial><TaskInventory /><ObjectFlags>0</ObjectFlags><UUID><Guid>10542a38-5b37-4568-b774-7f5f0d8211b8</Guid></UUID><LocalId>1269920870</LocalId><Name>block</Name><Material>3</Material><PassTouches>false</PassTouches><RegionHandle>1099511628032000</RegionHandle><ScriptAccessPin>0</ScriptAccessPin><PlaySoundSlavePrims /><LoopSoundSlavePrims /><GroupPosition><X>76</X><Y>88</Y><Z>21.75</Z></GroupPosition><OffsetPosition><X>-2.88322449</X><Y>7.999989</Y><Z>-0.6831332</Z></OffsetPosition><RotationOffset><X>1.07222113E-05</X><Y>-0.7071177</Y><Z>1.07056612E-05</Z><W>0.707095861</W></RotationOffset><Velocity><X>0</X><Y>0</Y><Z>0</Z></Velocity><AngularVelocity><X>0</X><Y>0</Y><Z>0</Z></AngularVelocity><Acceleration><X>0</X><Y>0</Y><Z>0</Z></Acceleration><Description /><Color /><Text /><SitName /><TouchName /><LinkNum>11</LinkNum><ClickAction>0</ClickAction><Shape><ProfileCurve>1</ProfileCurve><TextureEntry>xzptR3TPRgyWH/Ttp1ZR9gAAAAAAAAAAgD8AAACAPwAAAAAAAAAAAADAAAAAAA==</TextureEntry><ExtraParams>AA==</ExtraParams><PathBegin>0</PathBegin><PathCurve>16</PathCurve><PathEnd>0</PathEnd><PathRadiusOffset>0</PathRadiusOffset><PathRevolutions>0</PathRevolutions><PathScaleX>100</PathScaleX><PathScaleY>100</PathScaleY><PathShearX>0</PathShearX><PathShearY>0</PathShearY><PathSkew>0</PathSkew><PathTaperX>0</PathTaperX><PathTaperY>0</PathTaperY><PathTwist>0</PathTwist><PathTwistBegin>0</PathTwistBegin><PCode>9</PCode><ProfileBegin>0</ProfileBegin><ProfileEnd>0</ProfileEnd><ProfileHollow>0</ProfileHollow><Scale><X>2</X><Y>8</Y><Z>1</Z></Scale><State>0</State><ProfileShape>Square</ProfileShape><HollowShape>Same</HollowShape><SculptTexture><Guid>00000000-0000-0000-0000-000000000000</Guid></SculptTexture><SculptType>0</SculptType><SculptData /><FlexiSoftness>0</FlexiSoftness><FlexiTension>0</FlexiTension><FlexiDrag>0</FlexiDrag><FlexiGravity>0</FlexiGravity><FlexiWind>0</FlexiWind><FlexiForceX>0</FlexiForceX><FlexiForceY>0</FlexiForceY><FlexiForceZ>0</FlexiForceZ><LightColorR>0</LightColorR><LightColorG>0</LightColorG><LightColorB>0</LightColorB><LightColorA>1</LightColorA><LightRadius>0</LightRadius><LightCutoff>0</LightCutoff><LightFalloff>0</LightFalloff><LightIntensity>1</LightIntensity><FlexiEntry>false</FlexiEntry><LightEntry>false</LightEntry><SculptEntry>false</SculptEntry></Shape><Scale><X>2</X><Y>8</Y><Z>1</Z></Scale><UpdateFlag>0</UpdateFlag><SitTargetOrientation><X>0</X><Y>0</Y><Z>0</Z><W>1</W></SitTargetOrientation><SitTargetPosition><X>0</X><Y>0</Y><Z>0</Z></SitTargetPosition><SitTargetPositionLL><X>0</X><Y>0</Y><Z>0</Z></SitTargetPositionLL><SitTargetOrientationLL><X>0</X><Y>0</Y><Z>0</Z><W>1</W></SitTargetOrientationLL><ParentID>1269920860</ParentID><CreationDate>1258746394</CreationDate><Category>0</Category><SalePrice>10</SalePrice><ObjectSaleType>0</ObjectSaleType><OwnershipCost>0</OwnershipCost><GroupID><Guid>19b9cf50-f667-4a97-806b-fec7d4363c46</Guid></GroupID><OwnerID><Guid>155adad4-8975-4706-b95f-fa75af0678c5</Guid></OwnerID><LastOwnerID><Guid>155adad4-8975-4706-b95f-fa75af0678c5</Guid></LastOwnerID><BaseMask>581632</BaseMask><OwnerMask>581632</OwnerMask><GroupMask>0</GroupMask><EveryoneMask>0</EveryoneMask><NextOwnerMask>581632</NextOwnerMask><Flags>None</Flags><CollisionSound><Guid>00000000-0000-0000-0000-000000000000</Guid></CollisionSound><CollisionSoundVolume>0</CollisionSoundVolume></SceneObjectPart><SceneObjectPart xmlns:xsi="http://www.w3.org/2001/XMLSchema-instance" xmlns:xsd="http://www.w3.org/2001/XMLSchema"><AllowedDrop>false</AllowedDrop><CreatorID><Guid>155adad4-8975-4706-b95f-fa75af0678c5</Guid></CreatorID><FolderID><Guid>09f851d9-745f-4a1c-aa4f-6621c8981dca</Guid></FolderID><InventorySerial>1</InventorySerial><TaskInventory /><ObjectFlags>0</ObjectFlags><UUID><Guid>09f851d9-745f-4a1c-aa4f-6621c8981dca</Guid></UUID><LocalId>1269920871</LocalId><Name>cz OV floor</Name><Material>3</Material><PassTouches>false</PassTouches><RegionHandle>1099511628032000</RegionHandle><ScriptAccessPin>0</ScriptAccessPin><PlaySoundSlavePrims /><LoopSoundSlavePrims /><GroupPosition><X>76</X><Y>88</Y><Z>21.75</Z></GroupPosition><OffsetPosition><X>0.0567736924</X><Y>14.9349995</Y><Z>-0.6831034</Z></OffsetPosition><RotationOffset><X>-0.2705979</X><Y>-0.6535473</Y><Z>0.270598143</Z><W>-0.653015554</W></RotationOffset><Velocity><X>0</X><Y>0</Y><Z>0</Z></Velocity><AngularVelocity><X>0</X><Y>0</Y><Z>0</Z></AngularVelocity><Acceleration><X>0</X><Y>0</Y><Z>0</Z></Acceleration><Description /><Color /><Text /><SitName /><TouchName /><LinkNum>12</LinkNum><ClickAction>0</ClickAction><Shape><ProfileCurve>1</ProfileCurve><TextureEntry>xzptR3TPRgyWH/Ttp1ZR9gAAAAAAAAAAgD8AAACAPwAAAAAAAAAAAADAAAAAAA==</TextureEntry><ExtraParams>AA==</ExtraParams><PathBegin>0</PathBegin><PathCurve>16</PathCurve><PathEnd>0</PathEnd><PathRadiusOffset>0</PathRadiusOffset><PathRevolutions>0</PathRevolutions><PathScaleX>100</PathScaleX><PathScaleY>115</PathScaleY><PathShearX>0</PathShearX><PathShearY>0</PathShearY><PathSkew>0</PathSkew><PathTaperX>0</PathTaperX><PathTaperY>0</PathTaperY><PathTwist>0</PathTwist><PathTwistBegin>0</PathTwistBegin><PCode>9</PCode><ProfileBegin>0</ProfileBegin><ProfileEnd>0</ProfileEnd><ProfileHollow>0</ProfileHollow><Scale><X>2</X><Y>9</Y><Z>0.71</Z></Scale><State>0</State><ProfileShape>Square</ProfileShape><HollowShape>Same</HollowShape><SculptTexture><Guid>00000000-0000-0000-0000-000000000000</Guid></SculptTexture><SculptType>0</SculptType><SculptData /><FlexiSoftness>0</FlexiSoftness><FlexiTension>0</FlexiTension><FlexiDrag>0</FlexiDrag><FlexiGravity>0</FlexiGravity><FlexiWind>0</FlexiWind><FlexiForceX>0</FlexiForceX><FlexiForceY>0</FlexiForceY><FlexiForceZ>0</FlexiForceZ><LightColorR>0</LightColorR><LightColorG>0</LightColorG><LightColorB>0</LightColorB><LightColorA>1</LightColorA><LightRadius>0</LightRadius><LightCutoff>0</LightCutoff><LightFalloff>0</LightFalloff><LightIntensity>1</LightIntensity><FlexiEntry>false</FlexiEntry><LightEntry>false</LightEntry><SculptEntry>false</SculptEntry></Shape><Scale><X>2</X><Y>9</Y><Z>0.71</Z></Scale><UpdateFlag>0</UpdateFlag><SitTargetOrientation><X>0</X><Y>0</Y><Z>0</Z><W>1</W></SitTargetOrientation><SitTargetPosition><X>0</X><Y>0</Y><Z>0</Z></SitTargetPosition><SitTargetPositionLL><X>0</X><Y>0</Y><Z>0</Z></SitTargetPositionLL><SitTargetOrientationLL><X>0</X><Y>0</Y><Z>0</Z><W>1</W></SitTargetOrientationLL><ParentID>1269920860</ParentID><CreationDate>1258746394</CreationDate><Category>0</Category><SalePrice>10</SalePrice><ObjectSaleType>0</ObjectSaleType><OwnershipCost>0</OwnershipCost><GroupID><Guid>19b9cf50-f667-4a97-806b-fec7d4363c46</Guid></GroupID><OwnerID><Guid>155adad4-8975-4706-b95f-fa75af0678c5</Guid></OwnerID><LastOwnerID><Guid>155adad4-8975-4706-b95f-fa75af0678c5</Guid></LastOwnerID><BaseMask>581632</BaseMask><OwnerMask>581632</OwnerMask><GroupMask>0</GroupMask><EveryoneMask>0</EveryoneMask><NextOwnerMask>581632</NextOwnerMask><Flags>None</Flags><CollisionSound><Guid>00000000-0000-0000-0000-000000000000</Guid></CollisionSound><CollisionSoundVolume>0</CollisionSoundVolume></SceneObjectPart><SceneObjectPart xmlns:xsi="http://www.w3.org/2001/XMLSchema-instance" xmlns:xsd="http://www.w3.org/2001/XMLSchema"><AllowedDrop>false</AllowedDrop><CreatorID><Guid>155adad4-8975-4706-b95f-fa75af0678c5</Guid></CreatorID><FolderID><Guid>37ee5231-84e3-46f1-829d-a4f5c1eb6424</Guid></FolderID><InventorySerial>1</InventorySerial><TaskInventory /><ObjectFlags>0</ObjectFlags><UUID><Guid>37ee5231-84e3-46f1-829d-a4f5c1eb6424</Guid></UUID><LocalId>1269920872</LocalId><Name>block</Name><Material>3</Material><PassTouches>false</PassTouches><RegionHandle>1099511628032000</RegionHandle><ScriptAccessPin>0</ScriptAccessPin><PlaySoundSlavePrims /><LoopSoundSlavePrims /><GroupPosition><X>76</X><Y>88</Y><Z>21.75</Z></GroupPosition><OffsetPosition><X>-2.883232</X><Y>-14.15646</Y><Z>-0.6831337</Z></OffsetPosition><RotationOffset><X>0.70710665</X><Y>1.06847519E-05</Y><Z>0.7071069</Z><W>-1.07431215E-05</W></RotationOffset><Velocity><X>0</X><Y>0</Y><Z>0</Z></Velocity><AngularVelocity><X>0</X><Y>0</Y><Z>0</Z></AngularVelocity><Acceleration><X>0</X><Y>0</Y><Z>0</Z></Acceleration><Description /><Color /><Text /><SitName /><TouchName /><LinkNum>13</LinkNum><ClickAction>0</ClickAction><Shape><ProfileCurve>1</ProfileCurve><TextureEntry>xzptR3TPRgyWH/Ttp1ZR9gAAAAAAAAAAgD8AAACAPwAAAAAAAAAAAADAAAAAAA==</TextureEntry><ExtraParams>AA==</ExtraParams><PathBegin>0</PathBegin><PathCurve>16</PathCurve><PathEnd>0</PathEnd><PathRadiusOffset>0</PathRadiusOffset><PathRevolutions>0</PathRevolutions><PathScaleX>100</PathScaleX><PathScaleY>112</PathScaleY><PathShearX>0</PathShearX><PathShearY>250</PathShearY><PathSkew>0</PathSkew><PathTaperX>0</PathTaperX><PathTaperY>0</PathTaperY><PathTwist>0</PathTwist><PathTwistBegin>0</PathTwistBegin><PCode>9</PCode><ProfileBegin>0</ProfileBegin><ProfileEnd>0</ProfileEnd><ProfileHollow>0</ProfileHollow><Scale><X>2</X><Y>8</Y><Z>1</Z></Scale><State>0</State><ProfileShape>Square</ProfileShape><HollowShape>Same</HollowShape><SculptTexture><Guid>00000000-0000-0000-0000-000000000000</Guid></SculptTexture><SculptType>0</SculptType><SculptData /><FlexiSoftness>0</FlexiSoftness><FlexiTension>0</FlexiTension><FlexiDrag>0</FlexiDrag><FlexiGravity>0</FlexiGravity><FlexiWind>0</FlexiWind><FlexiForceX>0</FlexiForceX><FlexiForceY>0</FlexiForceY><FlexiForceZ>0</FlexiForceZ><LightColorR>0</LightColorR><LightColorG>0</LightColorG><LightColorB>0</LightColorB><LightColorA>1</LightColorA><LightRadius>0</LightRadius><LightCutoff>0</LightCutoff><LightFalloff>0</LightFalloff><LightIntensity>1</LightIntensity><FlexiEntry>false</FlexiEntry><LightEntry>false</LightEntry><SculptEntry>false</SculptEntry></Shape><Scale><X>2</X><Y>8</Y><Z>1</Z></Scale><UpdateFlag>0</UpdateFlag><SitTargetOrientation><X>0</X><Y>0</Y><Z>0</Z><W>1</W></SitTargetOrientation><SitTargetPosition><X>0</X><Y>0</Y><Z>0</Z></SitTargetPosition><SitTargetPositionLL><X>0</X><Y>0</Y><Z>0</Z></SitTargetPositionLL><SitTargetOrientationLL><X>0</X><Y>0</Y><Z>0</Z><W>1</W></SitTargetOrientationLL><ParentID>1269920860</ParentID><CreationDate>1258746394</CreationDate><Category>0</Category><SalePrice>10</SalePrice><ObjectSaleType>0</ObjectSaleType><OwnershipCost>0</OwnershipCost><GroupID><Guid>19b9cf50-f667-4a97-806b-fec7d4363c46</Guid></GroupID><OwnerID><Guid>155adad4-8975-4706-b95f-fa75af0678c5</Guid></OwnerID><LastOwnerID><Guid>155adad4-8975-4706-b95f-fa75af0678c5</Guid></LastOwnerID><BaseMask>581632</BaseMask><OwnerMask>581632</OwnerMask><GroupMask>0</GroupMask><EveryoneMask>0</EveryoneMask><NextOwnerMask>581632</NextOwnerMask><Flags>None</Flags><CollisionSound><Guid>00000000-0000-0000-0000-000000000000</Guid></CollisionSound><CollisionSoundVolume>0</CollisionSoundVolume></SceneObjectPart><SceneObjectPart xmlns:xsi="http://www.w3.org/2001/XMLSchema-instance" xmlns:xsd="http://www.w3.org/2001/XMLSchema"><AllowedDrop>false</AllowedDrop><CreatorID><Guid>155adad4-8975-4706-b95f-fa75af0678c5</Guid></CreatorID><FolderID><Guid>c68101f8-0a50-4557-be83-b6549e1e21d1</Guid></FolderID><InventorySerial>1</InventorySerial><TaskInventory /><ObjectFlags>0</ObjectFlags><UUID><Guid>c68101f8-0a50-4557-be83-b6549e1e21d1</Guid></UUID><LocalId>1269920873</LocalId><Name>block</Name><Material>3</Material><PassTouches>false</PassTouches><RegionHandle>1099511628032000</RegionHandle><ScriptAccessPin>0</ScriptAccessPin><PlaySoundSlavePrims /><LoopSoundSlavePrims /><GroupPosition><X>76</X><Y>88</Y><Z>21.75</Z></GroupPosition><OffsetPosition><X>-2.88325572</X><Y>-7.08306456</Y><Z>-0.683133543</Z></OffsetPosition><RotationOffset><X>1.07222113E-05</X><Y>-0.7071177</Y><Z>1.07056612E-05</Z><W>0.707095861</W></RotationOffset><Velocity><X>0</X><Y>0</Y><Z>0</Z></Velocity><AngularVelocity><X>0</X><Y>0</Y><Z>0</Z></AngularVelocity><Acceleration><X>0</X><Y>0</Y><Z>0</Z></Acceleration><Description /><Color /><Text /><SitName /><TouchName /><LinkNum>14</LinkNum><ClickAction>0</ClickAction><Shape><ProfileCurve>1</ProfileCurve><TextureEntry>xzptR3TPRgyWH/Ttp1ZR9gAAAAAAAAAAgD8AAACAPwAAAAAAAAAAAADAAAAAAA==</TextureEntry><ExtraParams>AA==</ExtraParams><PathBegin>0</PathBegin><PathCurve>16</PathCurve><PathEnd>0</PathEnd><PathRadiusOffset>0</PathRadiusOffset><PathRevolutions>0</PathRevolutions><PathScaleX>100</PathScaleX><PathScaleY>100</PathScaleY><PathShearX>0</PathShearX><PathShearY>0</PathShearY><PathSkew>0</PathSkew><PathTaperX>0</PathTaperX><PathTaperY>0</PathTaperY><PathTwist>0</PathTwist><PathTwistBegin>0</PathTwistBegin><PCode>9</PCode><ProfileBegin>0</ProfileBegin><ProfileEnd>0</ProfileEnd><ProfileHollow>0</ProfileHollow><Scale><X>2</X><Y>6.16609955</Y><Z>1</Z></Scale><State>0</State><ProfileShape>Square</ProfileShape><HollowShape>Same</HollowShape><SculptTexture><Guid>00000000-0000-0000-0000-000000000000</Guid></SculptTexture><SculptType>0</SculptType><SculptData /><FlexiSoftness>0</FlexiSoftness><FlexiTension>0</FlexiTension><FlexiDrag>0</FlexiDrag><FlexiGravity>0</FlexiGravity><FlexiWind>0</FlexiWind><FlexiForceX>0</FlexiForceX><FlexiForceY>0</FlexiForceY><FlexiForceZ>0</FlexiForceZ><LightColorR>0</LightColorR><LightColorG>0</LightColorG><LightColorB>0</LightColorB><LightColorA>1</LightColorA><LightRadius>0</LightRadius><LightCutoff>0</LightCutoff><LightFalloff>0</LightFalloff><LightIntensity>1</LightIntensity><FlexiEntry>false</FlexiEntry><LightEntry>false</LightEntry><SculptEntry>false</SculptEntry></Shape><Scale><X>2</X><Y>6.16609955</Y><Z>1</Z></Scale><UpdateFlag>0</UpdateFlag><SitTargetOrientation><X>0</X><Y>0</Y><Z>0</Z><W>1</W></SitTargetOrientation><SitTargetPosition><X>0</X><Y>0</Y><Z>0</Z></SitTargetPosition><SitTargetPositionLL><X>0</X><Y>0</Y><Z>0</Z></SitTargetPositionLL><SitTargetOrientationLL><X>0</X><Y>0</Y><Z>0</Z><W>1</W></SitTargetOrientationLL><ParentID>1269920860</ParentID><CreationDate>1258746394</CreationDate><Category>0</Category><SalePrice>10</SalePrice><ObjectSaleType>0</ObjectSaleType><OwnershipCost>0</OwnershipCost><GroupID><Guid>19b9cf50-f667-4a97-806b-fec7d4363c46</Guid></GroupID><OwnerID><Guid>155adad4-8975-4706-b95f-fa75af0678c5</Guid></OwnerID><LastOwnerID><Guid>155adad4-8975-4706-b95f-fa75af0678c5</Guid></LastOwnerID><BaseMask>581632</BaseMask><OwnerMask>581632</OwnerMask><GroupMask>0</GroupMask><EveryoneMask>0</EveryoneMask><NextOwnerMask>581632</NextOwnerMask><Flags>None</Flags><CollisionSound><Guid>00000000-0000-0000-0000-000000000000</Guid></CollisionSound><CollisionSoundVolume>0</CollisionSoundVolume></SceneObjectPart><SceneObjectPart xmlns:xsi="http://www.w3.org/2001/XMLSchema-instance" xmlns:xsd="http://www.w3.org/2001/XMLSchema"><AllowedDrop>false</AllowedDrop><CreatorID><Guid>155adad4-8975-4706-b95f-fa75af0678c5</Guid></CreatorID><FolderID><Guid>f48d94eb-bd88-4f18-bed9-ea0e9da69aa6</Guid></FolderID><InventorySerial>1</InventorySerial><TaskInventory /><ObjectFlags>0</ObjectFlags><UUID><Guid>f48d94eb-bd88-4f18-bed9-ea0e9da69aa6</Guid></UUID><LocalId>1269920874</LocalId><Name>cz OV floor</Name><Material>3</Material><PassTouches>false</PassTouches><RegionHandle>1099511628032000</RegionHandle><ScriptAccessPin>0</ScriptAccessPin><PlaySoundSlavePrims /><LoopSoundSlavePrims /><GroupPosition><X>76</X><Y>88</Y><Z>21.75</Z></GroupPosition><OffsetPosition><X>-0.4282314</X><Y>-15.6332836</Y><Z>-0.683119059</Z></OffsetPosition><RotationOffset><X>-0.2705782</X><Y>-0.653289855</Y><Z>-0.270618021</Z><W>0.6532731</W></RotationOffset><Velocity><X>0</X><Y>0</Y><Z>0</Z></Velocity><AngularVelocity><X>0</X><Y>0</Y><Z>0</Z></AngularVelocity><Acceleration><X>0</X><Y>0</Y><Z>0</Z></Acceleration><Description /><Color /><Text /><SitName /><TouchName /><LinkNum>15</LinkNum><ClickAction>0</ClickAction><Shape><ProfileCurve>1</ProfileCurve><TextureEntry>xzptR3TPRgyWH/Ttp1ZR9gAAAAAAAAAAgD8AAACAPwAAAAAAAAAAAADAAAAAAA==</TextureEntry><ExtraParams>AA==</ExtraParams><PathBegin>0</PathBegin><PathCurve>16</PathCurve><PathEnd>0</PathEnd><PathRadiusOffset>0</PathRadiusOffset><PathRevolutions>0</PathRevolutions><PathScaleX>100</PathScaleX><PathScaleY>115</PathScaleY><PathShearX>0</PathShearX><PathShearY>0</PathShearY><PathSkew>0</PathSkew><PathTaperX>0</PathTaperX><PathTaperY>0</PathTaperY><PathTwist>0</PathTwist><PathTwistBegin>0</PathTwistBegin><PCode>9</PCode><ProfileBegin>0</ProfileBegin><ProfileEnd>0</ProfileEnd><ProfileHollow>0</ProfileHollow><Scale><X>2</X><Y>9</Y><Z>0.71</Z></Scale><State>0</State><ProfileShape>Square</ProfileShape><HollowShape>Same</HollowShape><SculptTexture><Guid>00000000-0000-0000-0000-000000000000</Guid></SculptTexture><SculptType>0</SculptType><SculptData /><FlexiSoftness>0</FlexiSoftness><FlexiTension>0</FlexiTension><FlexiDrag>0</FlexiDrag><FlexiGravity>0</FlexiGravity><FlexiWind>0</FlexiWind><FlexiForceX>0</FlexiForceX><FlexiForceY>0</FlexiForceY><FlexiForceZ>0</FlexiForceZ><LightColorR>0</LightColorR><LightColorG>0</LightColorG><LightColorB>0</LightColorB><LightColorA>1</LightColorA><LightRadius>0</LightRadius><LightCutoff>0</LightCutoff><LightFalloff>0</LightFalloff><LightIntensity>1</LightIntensity><FlexiEntry>false</FlexiEntry><LightEntry>false</LightEntry><SculptEntry>false</SculptEntry></Shape><Scale><X>2</X><Y>9</Y><Z>0.71</Z></Scale><UpdateFlag>0</UpdateFlag><SitTargetOrientation><X>0</X><Y>0</Y><Z>0</Z><W>1</W></SitTargetOrientation><SitTargetPosition><X>0</X><Y>0</Y><Z>0</Z></SitTargetPosition><SitTargetPositionLL><X>0</X><Y>0</Y><Z>0</Z></SitTargetPositionLL><SitTargetOrientationLL><X>0</X><Y>0</Y><Z>0</Z><W>1</W></SitTargetOrientationLL><ParentID>1269920860</ParentID><CreationDate>1258746394</CreationDate><Category>0</Category><SalePrice>10</SalePrice><ObjectSaleType>0</ObjectSaleType><OwnershipCost>0</OwnershipCost><GroupID><Guid>19b9cf50-f667-4a97-806b-fec7d4363c46</Guid></GroupID><OwnerID><Guid>155adad4-8975-4706-b95f-fa75af0678c5</Guid></OwnerID><LastOwnerID><Guid>155adad4-8975-4706-b95f-fa75af0678c5</Guid></LastOwnerID><BaseMask>581632</BaseMask><OwnerMask>581632</OwnerMask><GroupMask>0</GroupMask><EveryoneMask>0</EveryoneMask><NextOwnerMask>581632</NextOwnerMask><Flags>None</Flags><CollisionSound><Guid>00000000-0000-0000-0000-000000000000</Guid></CollisionSound><CollisionSoundVolume>0</CollisionSoundVolume></SceneObjectPart></OtherParts></SceneObjectGroup>